[
  {
    "time": 1777198917.833102
  },
  {
    "time": 1777199430.130216
  },
  {
    "time": 1777199820.193446
  },
  {
    "time": 1777200776.788511
  },
  {
    "time": 1777201221.704992
  },
  {
    "time": 1777201331.483386
  },
  {
    "time": 1777202095.0244758
  },
  {
    "time": 1777202649.269707
  },
  {
    "time": 1777203033.473932
  },
  {
    "time": 1777203228.799436
  },
  {
    "time": 1777203620.4174888,
    "visitor_id": "99f5f76f-836a-4c33-9a69-93957b19e15c"
  },
  {
    "time": 1777203710.6043,
    "visitor_id": "9ec64a1b-73fa-45b8-aba7-f4a3906e3b4c"
  },
  {
    "time": 1777204213.767669,
    "visitor_id": "71c30797-c43e-484d-bb73-7f100d8abb14"
  },
  {
    "time": 1777204256.788809,
    "visitor_id": "ca28b511-600c-4d7a-bfed-a82d883f0754"
  },
  {
    "time": 1777204563.353544,
    "visitor_id": "70656c00-042a-4660-9350-59a4e1d66eae"
  },
  {
    "time": 1777204579.5484061,
    "visitor_id": "9bdc94f3-3cab-4573-a717-827833619b7d"
  },
  {
    "time": 1777205055.189837,
    "visitor_id": "8b185857-83be-4455-9170-770affb7e46b"
  },
  {
    "time": 1777205575.7698581,
    "visitor_id": "8b185857-83be-4455-9170-770affb7e46b"
  },
  {
    "time": 1777205598.7632499,
    "visitor_id": "8b185857-83be-4455-9170-770affb7e46b"
  },
  {
    "time": 1777206284.6073658,
    "visitor_id": "8b185857-83be-4455-9170-770affb7e46b"
  },
  {
    "time": 1777207989.624971,
    "visitor_id": "8b185857-83be-4455-9170-770affb7e46b",
    "country": "Local"
  },
  {
    "time": 1777208041.6238139,
    "visitor_id": "8b185857-83be-4455-9170-770affb7e46b",
    "country": "Local"
  },
  {
    "time": 1777208128.378975,
    "visitor_id": "8b185857-83be-4455-9170-770affb7e46b",
    "country": "Local"
  },
  {
    "time": 1777208412.9452422,
    "visitor_id": "6926b08f-02ed-47bd-a583-b9082c7485f5",
    "country": "Local"
  },
  {
    "time": 1777210364.6053572,
    "visitor_id": "8b185857-83be-4455-9170-770affb7e46b",
    "country": "Local"
  },
  {
    "time": 1777264763.2294762,
    "visitor_id": "8b185857-83be-4455-9170-770affb7e46b",
    "country": "Local"
  },
  {
    "time": 1777272719.309472,
    "visitor_id": "8b185857-83be-4455-9170-770affb7e46b",
    "country": "Local"
  },
  {
    "time": 1777273159.3545668,
    "visitor_id": "8b185857-83be-4455-9170-770affb7e46b",
    "country": "Local"
  },
  {
    "time": 1777273638.9129589,
    "visitor_id": "8b185857-83be-4455-9170-770affb7e46b",
    "country": "Local"
  },
  {
    "time": 1777273922.084641,
    "visitor_id": "8b185857-83be-4455-9170-770affb7e46b",
    "country": "Local"
  },
  {
    "time": 1777273930.8416378,
    "visitor_id": "8b185857-83be-4455-9170-770affb7e46b",
    "country": "Local"
  },
  {
    "time": 1777274322.43813,
    "visitor_id": "8b185857-83be-4455-9170-770affb7e46b",
    "country": "Local"
  },
  {
    "time": 1777274337.234448,
    "visitor_id": "8b185857-83be-4455-9170-770affb7e46b",
    "country": "Local"
  },
  {
    "time": 1777274341.095092,
    "visitor_id": "8b185857-83be-4455-9170-770affb7e46b",
    "country": "Local"
  },
  {
    "time": 1777274343.417001,
    "visitor_id": "8b185857-83be-4455-9170-770affb7e46b",
    "country": "Local"
  },
  {
    "time": 1777274355.62784,
    "visitor_id": "8b185857-83be-4455-9170-770affb7e46b",
    "country": "Local"
  },
  {
    "time": 1777274357.9054642,
    "visitor_id": "8b185857-83be-4455-9170-770affb7e46b",
    "country": "Local"
  },
  {
    "time": 1777274359.021902,
    "visitor_id": "8b185857-83be-4455-9170-770affb7e46b",
    "country": "Local"
  },
  {
    "time": 1777274362.152055,
    "visitor_id": "8b185857-83be-4455-9170-770affb7e46b",
    "country": "Local"
  },
  {
    "time": 1777274364.243456,
    "visitor_id": "8b185857-83be-4455-9170-770affb7e46b",
    "country": "Local"
  },
  {
    "time": 1777274779.154923,
    "visitor_id": "8b185857-83be-4455-9170-770affb7e46b",
    "country": "Local"
  },
  {
    "time": 1777275044.811409,
    "visitor_id": "8b185857-83be-4455-9170-770affb7e46b",
    "country": "Local"
  },
  {
    "time": 1777275051.7713852,
    "visitor_id": "8b185857-83be-4455-9170-770affb7e46b",
    "country": "Local"
  },
  {
    "time": 1777275053.184739,
    "visitor_id": "8b185857-83be-4455-9170-770affb7e46b",
    "country": "Local"
  },
  {
    "time": 1777275054.401674,
    "visitor_id": "8b185857-83be-4455-9170-770affb7e46b",
    "country": "Local"
  },
  {
    "time": 1777275055.430374,
    "visitor_id": "8b185857-83be-4455-9170-770affb7e46b",
    "country": "Local"
  },
  {
    "time": 1777275056.569618,
    "visitor_id": "8b185857-83be-4455-9170-770affb7e46b",
    "country": "Local"
  },
  {
    "time": 1777275063.215656,
    "visitor_id": "8b185857-83be-4455-9170-770affb7e46b",
    "country": "Local"
  },
  {
    "time": 1777275064.284539,
    "visitor_id": "8b185857-83be-4455-9170-770affb7e46b",
    "country": "Local"
  },
  {
    "time": 1777275065.24925,
    "visitor_id": "8b185857-83be-4455-9170-770affb7e46b",
    "country": "Local"
  },
  {
    "time": 1777275065.737699,
    "visitor_id": "8b185857-83be-4455-9170-770affb7e46b",
    "country": "Local"
  },
  {
    "time": 1777275165.1021068,
    "visitor_id": "8b185857-83be-4455-9170-770affb7e46b",
    "country": "Local"
  },
  {
    "time": 1777275179.900217,
    "visitor_id": "8b185857-83be-4455-9170-770affb7e46b",
    "country": "Local"
  },
  {
    "time": 1777275196.157933,
    "visitor_id": "8b185857-83be-4455-9170-770affb7e46b",
    "country": "Local"
  },
  {
    "time": 1777275383.834395,
    "visitor_id": "8b185857-83be-4455-9170-770affb7e46b",
    "country": "Local"
  },
  {
    "time": 1777308869.8099542,
    "visitor_id": "8b185857-83be-4455-9170-770affb7e46b",
    "country": "Local"
  },
  {
    "time": 1777337718.255504,
    "visitor_id": "8b185857-83be-4455-9170-770affb7e46b",
    "country": "Local"
  },
  {
    "time": 1777337725.4971461,
    "visitor_id": "8b185857-83be-4455-9170-770affb7e46b",
    "country": "Local"
  },
  {
    "time": 1777337833.937728,
    "visitor_id": "8b185857-83be-4455-9170-770affb7e46b",
    "country": "Local"
  },
  {
    "time": 1777337907.4839098,
    "visitor_id": "8b185857-83be-4455-9170-770affb7e46b",
    "country": "Local"
  },
  {
    "time": 1777338005.723855,
    "visitor_id": "8b185857-83be-4455-9170-770affb7e46b",
    "country": "Local"
  },
  {
    "time": 1777338009.1943412,
    "visitor_id": "8b185857-83be-4455-9170-770affb7e46b",
    "country": "Local"
  },
  {
    "time": 1777338025.866356,
    "visitor_id": "8b185857-83be-4455-9170-770affb7e46b",
    "country": "Local"
  },
  {
    "time": 1777338104.213683,
    "visitor_id": "8b185857-83be-4455-9170-770affb7e46b",
    "country": "Local"
  },
  {
    "time": 1777360726.8813398,
    "visitor_id": "8b185857-83be-4455-9170-770affb7e46b",
    "country": "Local"
  },
  {
    "time": 1777362313.332267,
    "visitor_id": "8b185857-83be-4455-9170-770affb7e46b",
    "country": "Local"
  },
  {
    "time": 1777362840.0888479,
    "visitor_id": "8b185857-83be-4455-9170-770affb7e46b",
    "country": "Local"
  },
  {
    "time": 1777362846.9852102,
    "visitor_id": "8b185857-83be-4455-9170-770affb7e46b",
    "country": "Local"
  },
  {
    "time": 1777363127.8211148,
    "visitor_id": "8b185857-83be-4455-9170-770affb7e46b",
    "country": "Local"
  },
  {
    "time": 1777365186.621801,
    "visitor_id": "8b185857-83be-4455-9170-770affb7e46b",
    "country": "Local"
  },
  {
    "time": 1777365385.679034,
    "visitor_id": "8b185857-83be-4455-9170-770affb7e46b",
    "country": "Local"
  },
  {
    "time": 1777365462.0902588,
    "visitor_id": "8b185857-83be-4455-9170-770affb7e46b",
    "country": "Local"
  },
  {
    "time": 1777365666.1719732,
    "visitor_id": "8b185857-83be-4455-9170-770affb7e46b",
    "country": "Local"
  },
  {
    "time": 1777366158.0152671,
    "visitor_id": "8b185857-83be-4455-9170-770affb7e46b",
    "country": "Local"
  },
  {
    "time": 1777366309.08656,
    "visitor_id": "8b185857-83be-4455-9170-770affb7e46b",
    "country": "Local"
  },
  {
    "time": 1777366310.596056,
    "visitor_id": "8b185857-83be-4455-9170-770affb7e46b",
    "country": "Local"
  },
  {
    "time": 1777366315.02994,
    "visitor_id": "8b185857-83be-4455-9170-770affb7e46b",
    "country": "Local"
  },
  {
    "time": 1777366591.276566,
    "visitor_id": "8b185857-83be-4455-9170-770affb7e46b",
    "country": "Local"
  },
  {
    "time": 1777367478.6693819,
    "visitor_id": "8b185857-83be-4455-9170-770affb7e46b",
    "country": "Local"
  },
  {
    "time": 1777367483.351336,
    "visitor_id": "8b185857-83be-4455-9170-770affb7e46b",
    "country": "Local"
  },
  {
    "time": 1777368747.48591,
    "visitor_id": "8b185857-83be-4455-9170-770affb7e46b",
    "country": "Local"
  },
  {
    "time": 1777368770.738709,
    "visitor_id": "8b185857-83be-4455-9170-770affb7e46b",
    "country": "Local"
  },
  {
    "time": 1777368777.8172338,
    "visitor_id": "8b185857-83be-4455-9170-770affb7e46b",
    "country": "Local"
  },
  {
    "time": 1777369338.11436,
    "visitor_id": "8b185857-83be-4455-9170-770affb7e46b",
    "country": "Local"
  },
  {
    "time": 1777369788.9516459,
    "visitor_id": "8b185857-83be-4455-9170-770affb7e46b",
    "country": "Local"
  },
  {
    "time": 1777371752.214766,
    "visitor_id": "8b185857-83be-4455-9170-770affb7e46b",
    "country": "Local"
  },
  {
    "time": 1777371767.793476,
    "visitor_id": "8b185857-83be-4455-9170-770affb7e46b",
    "country": "Local"
  },
  {
    "time": 1777371780.993797,
    "visitor_id": "8b185857-83be-4455-9170-770affb7e46b",
    "country": "Local"
  },
  {
    "time": 1777371799.946086,
    "visitor_id": "8b185857-83be-4455-9170-770affb7e46b",
    "country": "Local"
  },
  {
    "time": 1777371818.417017,
    "visitor_id": "8b185857-83be-4455-9170-770affb7e46b",
    "country": "Local"
  },
  {
    "time": 1777371820.5756748,
    "visitor_id": "8b185857-83be-4455-9170-770affb7e46b",
    "country": "Local"
  },
  {
    "time": 1777371821.900457,
    "visitor_id": "8b185857-83be-4455-9170-770affb7e46b",
    "country": "Local"
  },
  {
    "time": 1777371822.217359,
    "visitor_id": "8b185857-83be-4455-9170-770affb7e46b",
    "country": "Local"
  },
  {
    "time": 1777371822.7121458,
    "visitor_id": "8b185857-83be-4455-9170-770affb7e46b",
    "country": "Local"
  },
  {
    "time": 1777372200.136238,
    "visitor_id": "8b185857-83be-4455-9170-770affb7e46b",
    "country": "Local"
  },
  {
    "time": 1777372370.6747992,
    "visitor_id": "8b185857-83be-4455-9170-770affb7e46b",
    "country": "Local"
  },
  {
    "time": 1777374026.2557518,
    "visitor_id": "8b185857-83be-4455-9170-770affb7e46b",
    "country": "Local"
  },
  {
    "time": 1777374098.0738711,
    "visitor_id": "8b185857-83be-4455-9170-770affb7e46b",
    "country": "Local"
  },
  {
    "time": 1777374473.305293,
    "visitor_id": "8b185857-83be-4455-9170-770affb7e46b",
    "country": "Local"
  },
  {
    "time": 1777374491.1737962,
    "visitor_id": "8b185857-83be-4455-9170-770affb7e46b",
    "country": "Local"
  },
  {
    "time": 1777374946.527454,
    "visitor_id": "8b185857-83be-4455-9170-770affb7e46b",
    "country": "Local"
  },
  {
    "time": 1777375177.342643,
    "visitor_id": "8b185857-83be-4455-9170-770affb7e46b",
    "country": "Local"
  },
  {
    "time": 1777375181.8549702,
    "visitor_id": "8b185857-83be-4455-9170-770affb7e46b",
    "country": "Local"
  },
  {
    "time": 1777375351.696544,
    "visitor_id": "8b185857-83be-4455-9170-770affb7e46b",
    "country": "Local"
  },
  {
    "time": 1777375410.954619,
    "visitor_id": "8b185857-83be-4455-9170-770affb7e46b",
    "country": "Local"
  },
  {
    "time": 1777375418.783731,
    "visitor_id": "8b185857-83be-4455-9170-770affb7e46b",
    "country": "Local"
  },
  {
    "time": 1777375550.037518,
    "visitor_id": "8b185857-83be-4455-9170-770affb7e46b",
    "country": "Local"
  },
  {
    "time": 1777404437.774035,
    "visitor_id": "8b185857-83be-4455-9170-770affb7e46b",
    "country": "Local"
  },
  {
    "time": 1777404702.373583,
    "visitor_id": "8b185857-83be-4455-9170-770affb7e46b",
    "country": "Local"
  },
  {
    "time": 1777404920.283595,
    "visitor_id": "8b185857-83be-4455-9170-770affb7e46b",
    "country": "Local"
  },
  {
    "time": 1777405420.990894,
    "visitor_id": "8b185857-83be-4455-9170-770affb7e46b",
    "country": "Local"
  },
  {
    "time": 1777405504.2580109,
    "visitor_id": "8b185857-83be-4455-9170-770affb7e46b",
    "country": "Local"
  },
  {
    "time": 1777405670.007102,
    "visitor_id": "8b185857-83be-4455-9170-770affb7e46b",
    "country": "Local"
  },
  {
    "time": 1777406684.03808,
    "visitor_id": "8b185857-83be-4455-9170-770affb7e46b",
    "country": "Local"
  },
  {
    "time": 1777406821.4827561,
    "visitor_id": "8b185857-83be-4455-9170-770affb7e46b",
    "country": "Local"
  },
  {
    "time": 1777407181.284559,
    "visitor_id": "8b185857-83be-4455-9170-770affb7e46b",
    "country": "Local"
  },
  {
    "time": 1777407184.877762,
    "visitor_id": "8b185857-83be-4455-9170-770affb7e46b",
    "country": "Local"
  },
  {
    "time": 1777407664.104447,
    "visitor_id": "8b185857-83be-4455-9170-770affb7e46b",
    "country": "Local"
  },
  {
    "time": 1777407923.74737,
    "visitor_id": "8b185857-83be-4455-9170-770affb7e46b",
    "country": "Local"
  },
  {
    "time": 1777407949.324796,
    "visitor_id": "8b185857-83be-4455-9170-770affb7e46b",
    "country": "Local"
  },
  {
    "time": 1777408245.912989,
    "visitor_id": "8b185857-83be-4455-9170-770affb7e46b",
    "country": "Local"
  },
  {
    "time": 1777408923.054374,
    "visitor_id": "8b185857-83be-4455-9170-770affb7e46b",
    "country": "Local"
  },
  {
    "time": 1777409275.76803,
    "visitor_id": "8b185857-83be-4455-9170-770affb7e46b",
    "country": "Local"
  },
  {
    "time": 1777409312.468746,
    "visitor_id": "8b185857-83be-4455-9170-770affb7e46b",
    "country": "Local"
  },
  {
    "time": 1777409948.472663,
    "visitor_id": "8b185857-83be-4455-9170-770affb7e46b",
    "country": "Local"
  },
  {
    "time": 1777410094.638237,
    "visitor_id": "8b185857-83be-4455-9170-770affb7e46b",
    "country": "Local"
  },
  {
    "time": 1777410099.309817,
    "visitor_id": "8b185857-83be-4455-9170-770affb7e46b",
    "country": "Local"
  },
  {
    "time": 1777507410.692501,
    "visitor_id": "8b185857-83be-4455-9170-770affb7e46b",
    "country": "Local"
  },
  {
    "time": 1777507719.724884,
    "visitor_id": "8b185857-83be-4455-9170-770affb7e46b",
    "country": "Local"
  },
  {
    "time": 1777507722.2747672,
    "visitor_id": "8b185857-83be-4455-9170-770affb7e46b",
    "country": "Local"
  },
  {
    "time": 1777536831.4548879,
    "visitor_id": "dd065251-06d9-4b7f-9013-914470feec6b",
    "country": "Local"
  },
  {
    "time": 1777537463.948257,
    "visitor_id": "dd065251-06d9-4b7f-9013-914470feec6b",
    "country": "Local"
  },
  {
    "time": 1777537469.115241,
    "visitor_id": "dd065251-06d9-4b7f-9013-914470feec6b",
    "country": "Local"
  },
  {
    "time": 1777537469.981256,
    "visitor_id": "dd065251-06d9-4b7f-9013-914470feec6b",
    "country": "Local"
  },
  {
    "time": 1777537564.8954391,
    "visitor_id": "1cae6bb3-bcd3-4242-9266-0b870288e609",
    "country": "Local"
  },
  {
    "time": 1777537675.223657,
    "visitor_id": "1cae6bb3-bcd3-4242-9266-0b870288e609",
    "country": "Local"
  },
  {
    "time": 1777537735.0239239,
    "visitor_id": "1cae6bb3-bcd3-4242-9266-0b870288e609",
    "country": "Local"
  },
  {
    "time": 1777537789.496914,
    "visitor_id": "1cae6bb3-bcd3-4242-9266-0b870288e609",
    "country": "Local"
  },
  {
    "time": 1777537855.5636559,
    "visitor_id": "1cae6bb3-bcd3-4242-9266-0b870288e609",
    "country": "Local"
  },
  {
    "time": 1777537938.994564,
    "visitor_id": "1cae6bb3-bcd3-4242-9266-0b870288e609",
    "country": "Local"
  },
  {
    "time": 1777538463.4068952,
    "visitor_id": "1cae6bb3-bcd3-4242-9266-0b870288e609",
    "country": "Local"
  },
  {
    "time": 1777538940.038999,
    "visitor_id": "1cae6bb3-bcd3-4242-9266-0b870288e609",
    "country": "Local"
  },
  {
    "time": 1777538959.3228831,
    "visitor_id": "1cae6bb3-bcd3-4242-9266-0b870288e609",
    "country": "Local"
  },
  {
    "time": 1777539264.302614,
    "visitor_id": "1cae6bb3-bcd3-4242-9266-0b870288e609",
    "country": "Local"
  },
  {
    "time": 1777539402.072145,
    "visitor_id": "1cae6bb3-bcd3-4242-9266-0b870288e609",
    "country": "Local"
  },
  {
    "time": 1777539526.033159,
    "visitor_id": "1cae6bb3-bcd3-4242-9266-0b870288e609",
    "country": "Local"
  },
  {
    "time": 1777539538.807499,
    "visitor_id": "1cae6bb3-bcd3-4242-9266-0b870288e609",
    "country": "Local"
  },
  {
    "time": 1777539598.683532,
    "visitor_id": "1cae6bb3-bcd3-4242-9266-0b870288e609",
    "country": "Local"
  },
  {
    "time": 1777539669.123144,
    "visitor_id": "1cae6bb3-bcd3-4242-9266-0b870288e609",
    "country": "Local"
  },
  {
    "time": 1777539695.187168,
    "visitor_id": "1cae6bb3-bcd3-4242-9266-0b870288e609",
    "country": "Local"
  },
  {
    "time": 1777539814.2516081,
    "visitor_id": "1cae6bb3-bcd3-4242-9266-0b870288e609",
    "country": "Local"
  },
  {
    "time": 1777540097.4158258,
    "visitor_id": "1cae6bb3-bcd3-4242-9266-0b870288e609",
    "country": "Local"
  },
  {
    "time": 1777540162.08393,
    "visitor_id": "1cae6bb3-bcd3-4242-9266-0b870288e609",
    "country": "Local"
  },
  {
    "time": 1777540289.6837912,
    "visitor_id": "1cae6bb3-bcd3-4242-9266-0b870288e609",
    "country": "Local"
  },
  {
    "time": 1777541094.82463,
    "visitor_id": "1cae6bb3-bcd3-4242-9266-0b870288e609",
    "country": "Local"
  },
  {
    "time": 1777541109.208222,
    "visitor_id": "1cae6bb3-bcd3-4242-9266-0b870288e609",
    "country": "Local"
  },
  {
    "time": 1777541111.1433432,
    "visitor_id": "1cae6bb3-bcd3-4242-9266-0b870288e609",
    "country": "Local"
  },
  {
    "time": 1777541346.035043,
    "visitor_id": "1cae6bb3-bcd3-4242-9266-0b870288e609",
    "country": "Local"
  },
  {
    "time": 1777541403.853931,
    "visitor_id": "1cae6bb3-bcd3-4242-9266-0b870288e609",
    "country": "Local"
  },
  {
    "time": 1777541483.722126,
    "visitor_id": "1cae6bb3-bcd3-4242-9266-0b870288e609",
    "country": "Local"
  },
  {
    "time": 1777541507.303969,
    "visitor_id": "1cae6bb3-bcd3-4242-9266-0b870288e609",
    "country": "Local"
  },
  {
    "time": 1777541508.554517,
    "visitor_id": "1cae6bb3-bcd3-4242-9266-0b870288e609",
    "country": "Local"
  },
  {
    "time": 1777542221.805399,
    "visitor_id": "1cae6bb3-bcd3-4242-9266-0b870288e609",
    "country": "Local"
  },
  {
    "time": 1777542237.860472,
    "visitor_id": "1cae6bb3-bcd3-4242-9266-0b870288e609",
    "country": "Local"
  },
  {
    "time": 1777542411.779389,
    "visitor_id": "1cae6bb3-bcd3-4242-9266-0b870288e609",
    "country": "Local"
  },
  {
    "time": 1777542425.937333,
    "visitor_id": "1cae6bb3-bcd3-4242-9266-0b870288e609",
    "country": "Local"
  },
  {
    "time": 1777542664.179692,
    "visitor_id": "1cae6bb3-bcd3-4242-9266-0b870288e609",
    "country": "Local"
  },
  {
    "time": 1777543098.36731,
    "visitor_id": "1cae6bb3-bcd3-4242-9266-0b870288e609",
    "country": "Local"
  },
  {
    "time": 1777543751.218986,
    "visitor_id": "1cae6bb3-bcd3-4242-9266-0b870288e609",
    "country": "Local"
  },
  {
    "time": 1777543888.355349,
    "visitor_id": "1cae6bb3-bcd3-4242-9266-0b870288e609",
    "country": "Local"
  },
  {
    "time": 1777543914.279808,
    "visitor_id": "1cae6bb3-bcd3-4242-9266-0b870288e609",
    "country": "Local"
  },
  {
    "time": 1777544131.553686,
    "visitor_id": "1cae6bb3-bcd3-4242-9266-0b870288e609",
    "country": "Local"
  },
  {
    "time": 1777544306.69874,
    "visitor_id": "1cae6bb3-bcd3-4242-9266-0b870288e609",
    "country": "Local"
  },
  {
    "time": 1777544310.36797,
    "visitor_id": "1cae6bb3-bcd3-4242-9266-0b870288e609",
    "country": "Local"
  },
  {
    "time": 1777544366.492049,
    "visitor_id": "1cae6bb3-bcd3-4242-9266-0b870288e609",
    "country": "Local"
  },
  {
    "time": 1777544375.830733,
    "visitor_id": "1cae6bb3-bcd3-4242-9266-0b870288e609",
    "country": "Local"
  },
  {
    "time": 1777544408.815899,
    "visitor_id": "1cae6bb3-bcd3-4242-9266-0b870288e609",
    "country": "Local"
  },
  {
    "time": 1777544463.826889,
    "visitor_id": "1cae6bb3-bcd3-4242-9266-0b870288e609",
    "country": "Local"
  },
  {
    "time": 1777545027.172708,
    "visitor_id": "1cae6bb3-bcd3-4242-9266-0b870288e609",
    "country": "Local"
  },
  {
    "time": 1777545113.525413,
    "visitor_id": "1cae6bb3-bcd3-4242-9266-0b870288e609",
    "country": "Local"
  },
  {
    "time": 1777545221.589443,
    "visitor_id": "1cae6bb3-bcd3-4242-9266-0b870288e609",
    "country": "Local"
  },
  {
    "time": 1777545750.7841122,
    "visitor_id": "1cae6bb3-bcd3-4242-9266-0b870288e609",
    "country": "Local"
  },
  {
    "time": 1777546556.50752,
    "visitor_id": "1cae6bb3-bcd3-4242-9266-0b870288e609",
    "country": "Local"
  },
  {
    "time": 1777567843.7717912,
    "visitor_id": "dd065251-06d9-4b7f-9013-914470feec6b",
    "country": "Local"
  },
  {
    "time": 1777567868.1877818,
    "visitor_id": "1cae6bb3-bcd3-4242-9266-0b870288e609",
    "country": "Local"
  },
  {
    "time": 1777567872.963625,
    "visitor_id": "1cae6bb3-bcd3-4242-9266-0b870288e609",
    "country": "Local"
  },
  {
    "time": 1777567906.68879,
    "visitor_id": "dd065251-06d9-4b7f-9013-914470feec6b",
    "country": "Local"
  },
  {
    "time": 1777567907.783701,
    "visitor_id": "dd065251-06d9-4b7f-9013-914470feec6b",
    "country": "Local"
  },
  {
    "time": 1777567908.5936341,
    "visitor_id": "dd065251-06d9-4b7f-9013-914470feec6b",
    "country": "Local"
  },
  {
    "time": 1777567909.403646,
    "visitor_id": "dd065251-06d9-4b7f-9013-914470feec6b",
    "country": "Local"
  },
  {
    "time": 1777567910.3896499,
    "visitor_id": "dd065251-06d9-4b7f-9013-914470feec6b",
    "country": "Local"
  },
  {
    "time": 1777567911.153127,
    "visitor_id": "dd065251-06d9-4b7f-9013-914470feec6b",
    "country": "Local"
  },
  {
    "time": 1777567923.497588,
    "visitor_id": "1cae6bb3-bcd3-4242-9266-0b870288e609",
    "country": "Local"
  },
  {
    "time": 1777568340.009022,
    "visitor_id": "1cae6bb3-bcd3-4242-9266-0b870288e609",
    "country": "Local"
  },
  {
    "time": 1777568360.81174,
    "visitor_id": "1cae6bb3-bcd3-4242-9266-0b870288e609",
    "country": "Local"
  },
  {
    "time": 1777568555.0824041,
    "visitor_id": "1cae6bb3-bcd3-4242-9266-0b870288e609",
    "country": "Local"
  },
  {
    "time": 1777568636.2476108,
    "visitor_id": "1cae6bb3-bcd3-4242-9266-0b870288e609",
    "country": "Local"
  },
  {
    "time": 1777568664.303083,
    "visitor_id": "1cae6bb3-bcd3-4242-9266-0b870288e609",
    "country": "Local"
  },
  {
    "time": 1777568825.075941,
    "visitor_id": "1cae6bb3-bcd3-4242-9266-0b870288e609",
    "country": "Local"
  },
  {
    "time": 1777568900.5254521,
    "visitor_id": "1cae6bb3-bcd3-4242-9266-0b870288e609",
    "country": "Local"
  },
  {
    "time": 1777569000.557757,
    "visitor_id": "1cae6bb3-bcd3-4242-9266-0b870288e609",
    "country": "Local"
  },
  {
    "time": 1777569547.964512,
    "visitor_id": "dd065251-06d9-4b7f-9013-914470feec6b",
    "country": "Local"
  },
  {
    "time": 1777671212.597585,
    "visitor_id": "dd065251-06d9-4b7f-9013-914470feec6b",
    "country": "Local"
  },
  {
    "time": 1777671223.616967,
    "visitor_id": "dd065251-06d9-4b7f-9013-914470feec6b",
    "country": "Local"
  },
  {
    "time": 1777671227.795975,
    "visitor_id": "dd065251-06d9-4b7f-9013-914470feec6b",
    "country": "Local"
  },
  {
    "time": 1777671249.259274,
    "visitor_id": "dd065251-06d9-4b7f-9013-914470feec6b",
    "country": "Local"
  },
  {
    "time": 1777671254.913099,
    "visitor_id": "dd065251-06d9-4b7f-9013-914470feec6b",
    "country": "Local"
  },
  {
    "time": 1777671258.097412,
    "visitor_id": "dd065251-06d9-4b7f-9013-914470feec6b",
    "country": "Local"
  },
  {
    "time": 1777671700.772233,
    "visitor_id": "1cae6bb3-bcd3-4242-9266-0b870288e609",
    "country": "Local"
  },
  {
    "time": 1777671929.5065641,
    "visitor_id": "1cae6bb3-bcd3-4242-9266-0b870288e609",
    "country": "Local"
  },
  {
    "time": 1777671936.380911,
    "visitor_id": "1cae6bb3-bcd3-4242-9266-0b870288e609",
    "country": "Local"
  },
  {
    "time": 1777672474.506082,
    "visitor_id": "1cae6bb3-bcd3-4242-9266-0b870288e609",
    "country": "Local"
  },
  {
    "time": 1777672487.92451,
    "visitor_id": "1cae6bb3-bcd3-4242-9266-0b870288e609",
    "country": "Local"
  },
  {
    "time": 1777672597.105296,
    "visitor_id": "1cae6bb3-bcd3-4242-9266-0b870288e609",
    "country": "Local"
  },
  {
    "time": 1777672601.467697,
    "visitor_id": "1cae6bb3-bcd3-4242-9266-0b870288e609",
    "country": "Local"
  },
  {
    "time": 1777672985.681495,
    "visitor_id": "1cae6bb3-bcd3-4242-9266-0b870288e609",
    "country": "Local"
  },
  {
    "time": 1777672996.5003572,
    "visitor_id": "1cae6bb3-bcd3-4242-9266-0b870288e609",
    "country": "Local"
  },
  {
    "time": 1777673020.2469141,
    "visitor_id": "1cae6bb3-bcd3-4242-9266-0b870288e609",
    "country": "Local"
  },
  {
    "time": 1777673079.613129,
    "visitor_id": "1cae6bb3-bcd3-4242-9266-0b870288e609",
    "country": "Local"
  },
  {
    "time": 1777673155.61998,
    "visitor_id": "1cae6bb3-bcd3-4242-9266-0b870288e609",
    "country": "Local"
  },
  {
    "time": 1777673163.651683,
    "visitor_id": "1cae6bb3-bcd3-4242-9266-0b870288e609",
    "country": "Local"
  },
  {
    "time": 1777673288.722882,
    "visitor_id": "1cae6bb3-bcd3-4242-9266-0b870288e609",
    "country": "Local"
  },
  {
    "time": 1777673295.494944,
    "visitor_id": "1cae6bb3-bcd3-4242-9266-0b870288e609",
    "country": "Local"
  },
  {
    "time": 1777673407.838611,
    "visitor_id": "1cae6bb3-bcd3-4242-9266-0b870288e609",
    "country": "Local"
  },
  {
    "time": 1777673414.8544362,
    "visitor_id": "1cae6bb3-bcd3-4242-9266-0b870288e609",
    "country": "Local"
  },
  {
    "time": 1777673442.647788,
    "visitor_id": "1cae6bb3-bcd3-4242-9266-0b870288e609",
    "country": "Local"
  },
  {
    "time": 1777673451.713881,
    "visitor_id": "dd065251-06d9-4b7f-9013-914470feec6b",
    "country": "Local"
  },
  {
    "time": 1777674139.782839,
    "visitor_id": "1cae6bb3-bcd3-4242-9266-0b870288e609",
    "country": "Local"
  },
  {
    "time": 1777674425.9164748,
    "visitor_id": "1cae6bb3-bcd3-4242-9266-0b870288e609",
    "country": "Local"
  },
  {
    "time": 1777674435.184196,
    "visitor_id": "1cae6bb3-bcd3-4242-9266-0b870288e609",
    "country": "Local"
  },
  {
    "time": 1777674465.954112,
    "visitor_id": "1cae6bb3-bcd3-4242-9266-0b870288e609",
    "country": "Local"
  },
  {
    "time": 1777674569.752586,
    "visitor_id": "1cae6bb3-bcd3-4242-9266-0b870288e609",
    "country": "Local"
  },
  {
    "time": 1777674703.398127,
    "visitor_id": "1cae6bb3-bcd3-4242-9266-0b870288e609",
    "country": "Local"
  },
  {
    "time": 1777769067.8835359,
    "visitor_id": "1cae6bb3-bcd3-4242-9266-0b870288e609",
    "country": "Local"
  },
  {
    "time": 1777769305.7817311,
    "visitor_id": "1cae6bb3-bcd3-4242-9266-0b870288e609",
    "country": "Local"
  },
  {
    "time": 1777770081.487502,
    "visitor_id": "1cae6bb3-bcd3-4242-9266-0b870288e609",
    "country": "Local"
  },
  {
    "time": 1777770108.792494,
    "visitor_id": "1cae6bb3-bcd3-4242-9266-0b870288e609",
    "country": "Local"
  },
  {
    "time": 1777770110.354557,
    "visitor_id": "1cae6bb3-bcd3-4242-9266-0b870288e609",
    "country": "Local"
  },
  {
    "time": 1777770193.823477,
    "visitor_id": "1cae6bb3-bcd3-4242-9266-0b870288e609",
    "country": "Local"
  },
  {
    "time": 1777770222.461636,
    "visitor_id": "1cae6bb3-bcd3-4242-9266-0b870288e609",
    "country": "Local"
  },
  {
    "time": 1777787383.951543,
    "visitor_id": "1cae6bb3-bcd3-4242-9266-0b870288e609",
    "country": "Local"
  },
  {
    "time": 1777788803.551397,
    "visitor_id": "1cae6bb3-bcd3-4242-9266-0b870288e609",
    "country": "Local"
  },
  {
    "time": 1777788817.816221,
    "visitor_id": "1cae6bb3-bcd3-4242-9266-0b870288e609",
    "country": "Local"
  },
  {
    "time": 1777789579.0234282,
    "visitor_id": "1cae6bb3-bcd3-4242-9266-0b870288e609",
    "country": "Local"
  },
  {
    "time": 1777789592.365767,
    "visitor_id": "1cae6bb3-bcd3-4242-9266-0b870288e609",
    "country": "Local"
  },
  {
    "time": 1777789602.2835681,
    "visitor_id": "1cae6bb3-bcd3-4242-9266-0b870288e609",
    "country": "Local"
  },
  {
    "time": 1777789676.939258,
    "visitor_id": "1cae6bb3-bcd3-4242-9266-0b870288e609",
    "country": "Local"
  },
  {
    "time": 1777790231.420623,
    "visitor_id": "1cae6bb3-bcd3-4242-9266-0b870288e609",
    "country": "Local"
  },
  {
    "time": 1777790245.219475,
    "visitor_id": "1cae6bb3-bcd3-4242-9266-0b870288e609",
    "country": "Local"
  },
  {
    "time": 1777790254.926244,
    "visitor_id": "1cae6bb3-bcd3-4242-9266-0b870288e609",
    "country": "Local"
  },
  {
    "time": 1777790255.8897731,
    "visitor_id": "1cae6bb3-bcd3-4242-9266-0b870288e609",
    "country": "Local"
  },
  {
    "time": 1777790256.831249,
    "visitor_id": "1cae6bb3-bcd3-4242-9266-0b870288e609",
    "country": "Local"
  },
  {
    "time": 1777790257.8601742,
    "visitor_id": "1cae6bb3-bcd3-4242-9266-0b870288e609",
    "country": "Local"
  },
  {
    "time": 1777790258.602657,
    "visitor_id": "1cae6bb3-bcd3-4242-9266-0b870288e609",
    "country": "Local"
  },
  {
    "time": 1777790259.087425,
    "visitor_id": "1cae6bb3-bcd3-4242-9266-0b870288e609",
    "country": "Local"
  },
  {
    "time": 1777790260.087404,
    "visitor_id": "1cae6bb3-bcd3-4242-9266-0b870288e609",
    "country": "Local"
  },
  {
    "time": 1777790266.6494951,
    "visitor_id": "1cae6bb3-bcd3-4242-9266-0b870288e609",
    "country": "Local"
  },
  {
    "time": 1777790267.6469078,
    "visitor_id": "1cae6bb3-bcd3-4242-9266-0b870288e609",
    "country": "Local"
  },
  {
    "time": 1777790269.419798,
    "visitor_id": "1cae6bb3-bcd3-4242-9266-0b870288e609",
    "country": "Local"
  },
  {
    "time": 1777790270.39359,
    "visitor_id": "1cae6bb3-bcd3-4242-9266-0b870288e609",
    "country": "Local"
  },
  {
    "time": 1777790271.6105332,
    "visitor_id": "1cae6bb3-bcd3-4242-9266-0b870288e609",
    "country": "Local"
  },
  {
    "time": 1777790272.080755,
    "visitor_id": "1cae6bb3-bcd3-4242-9266-0b870288e609",
    "country": "Local"
  },
  {
    "time": 1777790272.551855,
    "visitor_id": "1cae6bb3-bcd3-4242-9266-0b870288e609",
    "country": "Local"
  },
  {
    "time": 1777790273.6731179,
    "visitor_id": "1cae6bb3-bcd3-4242-9266-0b870288e609",
    "country": "Local"
  },
  {
    "time": 1777790277.0144808,
    "visitor_id": "1cae6bb3-bcd3-4242-9266-0b870288e609",
    "country": "Local"
  },
  {
    "time": 1777790280.540268,
    "visitor_id": "1cae6bb3-bcd3-4242-9266-0b870288e609",
    "country": "Local"
  },
  {
    "time": 1777790281.9324002,
    "visitor_id": "1cae6bb3-bcd3-4242-9266-0b870288e609",
    "country": "Local"
  },
  {
    "time": 1777790282.3695319,
    "visitor_id": "1cae6bb3-bcd3-4242-9266-0b870288e609",
    "country": "Local"
  },
  {
    "time": 1777790282.778267,
    "visitor_id": "1cae6bb3-bcd3-4242-9266-0b870288e609",
    "country": "Local"
  },
  {
    "time": 1777790283.275341,
    "visitor_id": "1cae6bb3-bcd3-4242-9266-0b870288e609",
    "country": "Local"
  },
  {
    "time": 1777790283.6826549,
    "visitor_id": "1cae6bb3-bcd3-4242-9266-0b870288e609",
    "country": "Local"
  },
  {
    "time": 1777790284.9744482,
    "visitor_id": "1cae6bb3-bcd3-4242-9266-0b870288e609",
    "country": "Local"
  },
  {
    "time": 1777790287.748497,
    "visitor_id": "1cae6bb3-bcd3-4242-9266-0b870288e609",
    "country": "Local"
  },
  {
    "time": 1777790291.4249191,
    "visitor_id": "1cae6bb3-bcd3-4242-9266-0b870288e609",
    "country": "Local"
  },
  {
    "time": 1777790292.495374,
    "visitor_id": "1cae6bb3-bcd3-4242-9266-0b870288e609",
    "country": "Local"
  },
  {
    "time": 1777790294.002265,
    "visitor_id": "1cae6bb3-bcd3-4242-9266-0b870288e609",
    "country": "Local"
  },
  {
    "time": 1777790294.976752,
    "visitor_id": "1cae6bb3-bcd3-4242-9266-0b870288e609",
    "country": "Local"
  },
  {
    "time": 1777790296.198808,
    "visitor_id": "1cae6bb3-bcd3-4242-9266-0b870288e609",
    "country": "Local"
  },
  {
    "time": 1777790297.095745,
    "visitor_id": "1cae6bb3-bcd3-4242-9266-0b870288e609",
    "country": "Local"
  },
  {
    "time": 1777790298.138059,
    "visitor_id": "1cae6bb3-bcd3-4242-9266-0b870288e609",
    "country": "Local"
  },
  {
    "time": 1777790299.0661519,
    "visitor_id": "1cae6bb3-bcd3-4242-9266-0b870288e609",
    "country": "Local"
  },
  {
    "time": 1777790300.328624,
    "visitor_id": "1cae6bb3-bcd3-4242-9266-0b870288e609",
    "country": "Local"
  },
  {
    "time": 1777790300.6727622,
    "visitor_id": "1cae6bb3-bcd3-4242-9266-0b870288e609",
    "country": "Local"
  },
  {
    "time": 1777790301.079535,
    "visitor_id": "1cae6bb3-bcd3-4242-9266-0b870288e609",
    "country": "Local"
  },
  {
    "time": 1777790301.568773,
    "visitor_id": "1cae6bb3-bcd3-4242-9266-0b870288e609",
    "country": "Local"
  },
  {
    "time": 1777790301.97514,
    "visitor_id": "1cae6bb3-bcd3-4242-9266-0b870288e609",
    "country": "Local"
  },
  {
    "time": 1777790302.458977,
    "visitor_id": "1cae6bb3-bcd3-4242-9266-0b870288e609",
    "country": "Local"
  },
  {
    "time": 1777790302.990777,
    "visitor_id": "1cae6bb3-bcd3-4242-9266-0b870288e609",
    "country": "Local"
  },
  {
    "time": 1777790306.537888,
    "visitor_id": "1cae6bb3-bcd3-4242-9266-0b870288e609",
    "country": "Local"
  },
  {
    "time": 1777790573.13831,
    "visitor_id": "1cae6bb3-bcd3-4242-9266-0b870288e609",
    "country": "Local"
  },
  {
    "time": 1777790589.328404,
    "visitor_id": "1cae6bb3-bcd3-4242-9266-0b870288e609",
    "country": "Local"
  },
  {
    "time": 1777790590.436474,
    "visitor_id": "1cae6bb3-bcd3-4242-9266-0b870288e609",
    "country": "Local"
  },
  {
    "time": 1777790600.985173,
    "visitor_id": "1cae6bb3-bcd3-4242-9266-0b870288e609",
    "country": "Local"
  },
  {
    "time": 1777790608.297432,
    "visitor_id": "1cae6bb3-bcd3-4242-9266-0b870288e609",
    "country": "Local"
  },
  {
    "time": 1777790648.6521358,
    "visitor_id": "1cae6bb3-bcd3-4242-9266-0b870288e609",
    "country": "Local"
  },
  {
    "time": 1777790877.3786829,
    "visitor_id": "1cae6bb3-bcd3-4242-9266-0b870288e609",
    "country": "Local"
  },
  {
    "time": 1777790905.174489,
    "visitor_id": "1cae6bb3-bcd3-4242-9266-0b870288e609",
    "country": "Local"
  },
  {
    "time": 1777790907.770462,
    "visitor_id": "1cae6bb3-bcd3-4242-9266-0b870288e609",
    "country": "Local"
  },
  {
    "time": 1777790908.210324,
    "visitor_id": "1cae6bb3-bcd3-4242-9266-0b870288e609",
    "country": "Local"
  },
  {
    "time": 1777790926.016393,
    "visitor_id": "1cae6bb3-bcd3-4242-9266-0b870288e609",
    "country": "Local"
  },
  {
    "time": 1777790927.0093608,
    "visitor_id": "1cae6bb3-bcd3-4242-9266-0b870288e609",
    "country": "Local"
  },
  {
    "time": 1777790943.4590342,
    "visitor_id": "1cae6bb3-bcd3-4242-9266-0b870288e609",
    "country": "Local"
  },
  {
    "time": 1777792242.02238,
    "visitor_id": "1cae6bb3-bcd3-4242-9266-0b870288e609",
    "country": "Local"
  },
  {
    "time": 1777792438.73103,
    "visitor_id": "1cae6bb3-bcd3-4242-9266-0b870288e609",
    "country": "Local"
  },
  {
    "time": 1777793213.8122182,
    "visitor_id": "1cae6bb3-bcd3-4242-9266-0b870288e609",
    "country": "Local"
  },
  {
    "time": 1777793251.2357361,
    "visitor_id": "1cae6bb3-bcd3-4242-9266-0b870288e609",
    "country": "Local"
  },
  {
    "time": 1777793929.7070248,
    "visitor_id": "1cae6bb3-bcd3-4242-9266-0b870288e609",
    "country": "Local"
  },
  {
    "time": 1777794301.343637,
    "visitor_id": "1cae6bb3-bcd3-4242-9266-0b870288e609",
    "country": "Local"
  },
  {
    "time": 1777794687.773021,
    "visitor_id": "1cae6bb3-bcd3-4242-9266-0b870288e609",
    "country": "Local"
  },
  {
    "time": 1777795018.110687,
    "visitor_id": "1cae6bb3-bcd3-4242-9266-0b870288e609",
    "country": "Local"
  },
  {
    "time": 1777795284.0466108,
    "visitor_id": "1cae6bb3-bcd3-4242-9266-0b870288e609",
    "country": "Local"
  },
  {
    "time": 1777795456.9404402,
    "visitor_id": "1cae6bb3-bcd3-4242-9266-0b870288e609",
    "country": "Local"
  },
  {
    "time": 1777795639.36337,
    "visitor_id": "1cae6bb3-bcd3-4242-9266-0b870288e609",
    "country": "Local"
  },
  {
    "time": 1777796394.685927,
    "visitor_id": "1cae6bb3-bcd3-4242-9266-0b870288e609",
    "country": "Local"
  },
  {
    "time": 1777797165.7582238,
    "visitor_id": "1cae6bb3-bcd3-4242-9266-0b870288e609",
    "country": "Local"
  },
  {
    "time": 1777797174.6748228,
    "visitor_id": "1cae6bb3-bcd3-4242-9266-0b870288e609",
    "country": "Local"
  },
  {
    "time": 1777797340.3737001,
    "visitor_id": "1cae6bb3-bcd3-4242-9266-0b870288e609",
    "country": "Local"
  },
  {
    "time": 1777797423.8445911,
    "visitor_id": "1cae6bb3-bcd3-4242-9266-0b870288e609",
    "country": "Local"
  },
  {
    "time": 1777797536.651073,
    "visitor_id": "1cae6bb3-bcd3-4242-9266-0b870288e609",
    "country": "Local"
  },
  {
    "time": 1777797711.206896,
    "visitor_id": "1cae6bb3-bcd3-4242-9266-0b870288e609",
    "country": "Local"
  },
  {
    "time": 1777797726.827668,
    "visitor_id": "1cae6bb3-bcd3-4242-9266-0b870288e609",
    "country": "Local"
  },
  {
    "time": 1777798055.790163,
    "visitor_id": "dd065251-06d9-4b7f-9013-914470feec6b",
    "country": "Local"
  },
  {
    "time": 1777798062.095735,
    "visitor_id": "dd065251-06d9-4b7f-9013-914470feec6b",
    "country": "Local"
  },
  {
    "time": 1777798065.0979788,
    "visitor_id": "dd065251-06d9-4b7f-9013-914470feec6b",
    "country": "Local"
  },
  {
    "time": 1777798067.64416,
    "visitor_id": "dd065251-06d9-4b7f-9013-914470feec6b",
    "country": "Local"
  },
  {
    "time": 1777798070.544254,
    "visitor_id": "dd065251-06d9-4b7f-9013-914470feec6b",
    "country": "Local"
  },
  {
    "time": 1777798081.724771,
    "visitor_id": "dd065251-06d9-4b7f-9013-914470feec6b",
    "country": "Local"
  },
  {
    "time": 1777798084.228203,
    "visitor_id": "dd065251-06d9-4b7f-9013-914470feec6b",
    "country": "Local"
  },
  {
    "time": 1777798084.970888,
    "visitor_id": "dd065251-06d9-4b7f-9013-914470feec6b",
    "country": "Local"
  },
  {
    "time": 1777798143.096529,
    "visitor_id": "1cae6bb3-bcd3-4242-9266-0b870288e609",
    "country": "Local"
  },
  {
    "time": 1777798154.345461,
    "visitor_id": "1cae6bb3-bcd3-4242-9266-0b870288e609",
    "country": "Local"
  },
  {
    "time": 1777798162.5669708,
    "visitor_id": "1cae6bb3-bcd3-4242-9266-0b870288e609",
    "country": "Local"
  },
  {
    "time": 1777798822.794184,
    "visitor_id": "1cae6bb3-bcd3-4242-9266-0b870288e609",
    "country": "Local"
  },
  {
    "time": 1777798831.298112,
    "visitor_id": "1cae6bb3-bcd3-4242-9266-0b870288e609",
    "country": "Local"
  },
  {
    "time": 1777798871.887121,
    "visitor_id": "1cae6bb3-bcd3-4242-9266-0b870288e609",
    "country": "Local"
  },
  {
    "time": 1777798891.018815,
    "visitor_id": "1cae6bb3-bcd3-4242-9266-0b870288e609",
    "country": "Local"
  },
  {
    "time": 1777798894.321301,
    "visitor_id": "1cae6bb3-bcd3-4242-9266-0b870288e609",
    "country": "Local"
  },
  {
    "time": 1777798899.8398662,
    "visitor_id": "1cae6bb3-bcd3-4242-9266-0b870288e609",
    "country": "Local"
  },
  {
    "time": 1777798913.288629,
    "visitor_id": "1cae6bb3-bcd3-4242-9266-0b870288e609",
    "country": "Local"
  },
  {
    "time": 1777798937.096422,
    "visitor_id": "1cae6bb3-bcd3-4242-9266-0b870288e609",
    "country": "Local"
  },
  {
    "time": 1777798951.26066,
    "visitor_id": "1cae6bb3-bcd3-4242-9266-0b870288e609",
    "country": "Local"
  },
  {
    "time": 1777799276.099833,
    "visitor_id": "1cae6bb3-bcd3-4242-9266-0b870288e609",
    "country": "Local"
  },
  {
    "time": 1777799302.683574,
    "visitor_id": "1cae6bb3-bcd3-4242-9266-0b870288e609",
    "country": "Local"
  },
  {
    "time": 1777799308.997094,
    "visitor_id": "1cae6bb3-bcd3-4242-9266-0b870288e609",
    "country": "Local"
  },
  {
    "time": 1777799333.168417,
    "visitor_id": "1cae6bb3-bcd3-4242-9266-0b870288e609",
    "country": "Local"
  },
  {
    "time": 1777799345.004863,
    "visitor_id": "1cae6bb3-bcd3-4242-9266-0b870288e609",
    "country": "Local"
  },
  {
    "time": 1777799351.027769,
    "visitor_id": "1cae6bb3-bcd3-4242-9266-0b870288e609",
    "country": "Local"
  },
  {
    "time": 1777799369.5697489,
    "visitor_id": "1cae6bb3-bcd3-4242-9266-0b870288e609",
    "country": "Local"
  },
  {
    "time": 1777799378.564109,
    "visitor_id": "1cae6bb3-bcd3-4242-9266-0b870288e609",
    "country": "Local"
  },
  {
    "time": 1777799412.2428842,
    "visitor_id": "1cae6bb3-bcd3-4242-9266-0b870288e609",
    "country": "Local"
  },
  {
    "time": 1777799423.4102468,
    "visitor_id": "1cae6bb3-bcd3-4242-9266-0b870288e609",
    "country": "Local"
  },
  {
    "time": 1777799432.192815,
    "visitor_id": "1cae6bb3-bcd3-4242-9266-0b870288e609",
    "country": "Local"
  },
  {
    "time": 1777799451.988912,
    "visitor_id": "1cae6bb3-bcd3-4242-9266-0b870288e609",
    "country": "Local"
  },
  {
    "time": 1777799488.475886,
    "visitor_id": "1cae6bb3-bcd3-4242-9266-0b870288e609",
    "country": "Local"
  },
  {
    "time": 1777799495.318678,
    "visitor_id": "1cae6bb3-bcd3-4242-9266-0b870288e609",
    "country": "Local"
  },
  {
    "time": 1777799496.9049191,
    "visitor_id": "1cae6bb3-bcd3-4242-9266-0b870288e609",
    "country": "Local"
  },
  {
    "time": 1777799503.426927,
    "visitor_id": "1cae6bb3-bcd3-4242-9266-0b870288e609",
    "country": "Local"
  },
  {
    "time": 1777799506.025617,
    "visitor_id": "1cae6bb3-bcd3-4242-9266-0b870288e609",
    "country": "Local"
  },
  {
    "time": 1777799515.051716,
    "visitor_id": "1cae6bb3-bcd3-4242-9266-0b870288e609",
    "country": "Local"
  },
  {
    "time": 1777799527.7838871,
    "visitor_id": "1cae6bb3-bcd3-4242-9266-0b870288e609",
    "country": "Local"
  },
  {
    "time": 1777799529.865866,
    "visitor_id": "1cae6bb3-bcd3-4242-9266-0b870288e609",
    "country": "Local"
  },
  {
    "time": 1777799618.5904078,
    "visitor_id": "1cae6bb3-bcd3-4242-9266-0b870288e609",
    "country": "Local"
  },
  {
    "time": 1777799830.0895119,
    "visitor_id": "1cae6bb3-bcd3-4242-9266-0b870288e609",
    "country": "Local"
  },
  {
    "time": 1777800119.1564102,
    "visitor_id": "1cae6bb3-bcd3-4242-9266-0b870288e609",
    "country": "Local"
  },
  {
    "time": 1777800136.9943979,
    "visitor_id": "1cae6bb3-bcd3-4242-9266-0b870288e609",
    "country": "Local"
  },
  {
    "time": 1777800142.5305622,
    "visitor_id": "1cae6bb3-bcd3-4242-9266-0b870288e609",
    "country": "Local"
  },
  {
    "time": 1777800378.056075,
    "visitor_id": "1cae6bb3-bcd3-4242-9266-0b870288e609",
    "country": "Local"
  },
  {
    "time": 1777800384.3563719,
    "visitor_id": "1cae6bb3-bcd3-4242-9266-0b870288e609",
    "country": "Local"
  },
  {
    "time": 1777800387.0957289,
    "visitor_id": "1cae6bb3-bcd3-4242-9266-0b870288e609",
    "country": "Local"
  },
  {
    "time": 1777800387.945947,
    "visitor_id": "1cae6bb3-bcd3-4242-9266-0b870288e609",
    "country": "Local"
  },
  {
    "time": 1777800388.4472551,
    "visitor_id": "1cae6bb3-bcd3-4242-9266-0b870288e609",
    "country": "Local"
  },
  {
    "time": 1777800388.989473,
    "visitor_id": "1cae6bb3-bcd3-4242-9266-0b870288e609",
    "country": "Local"
  },
  {
    "time": 1777800389.411096,
    "visitor_id": "1cae6bb3-bcd3-4242-9266-0b870288e609",
    "country": "Local"
  },
  {
    "time": 1777800389.849947,
    "visitor_id": "1cae6bb3-bcd3-4242-9266-0b870288e609",
    "country": "Local"
  },
  {
    "time": 1777800390.821068,
    "visitor_id": "1cae6bb3-bcd3-4242-9266-0b870288e609",
    "country": "Local"
  },
  {
    "time": 1777800391.698015,
    "visitor_id": "1cae6bb3-bcd3-4242-9266-0b870288e609",
    "country": "Local"
  },
  {
    "time": 1777800598.5729659,
    "visitor_id": "1cae6bb3-bcd3-4242-9266-0b870288e609",
    "country": "Local"
  },
  {
    "time": 1777800858.69173,
    "visitor_id": "1cae6bb3-bcd3-4242-9266-0b870288e609",
    "country": "Local"
  },
  {
    "time": 1777803862.4283469,
    "visitor_id": "1cae6bb3-bcd3-4242-9266-0b870288e609",
    "country": "Local"
  },
  {
    "time": 1777803868.689991,
    "visitor_id": "1cae6bb3-bcd3-4242-9266-0b870288e609",
    "country": "Local"
  },
  {
    "time": 1777803879.2554328,
    "visitor_id": "1cae6bb3-bcd3-4242-9266-0b870288e609",
    "country": "Local"
  },
  {
    "time": 1777803911.412385,
    "visitor_id": "1cae6bb3-bcd3-4242-9266-0b870288e609",
    "country": "Local"
  },
  {
    "time": 1777804084.508168,
    "visitor_id": "1cae6bb3-bcd3-4242-9266-0b870288e609",
    "country": "Local"
  },
  {
    "time": 1777804091.35241,
    "visitor_id": "1cae6bb3-bcd3-4242-9266-0b870288e609",
    "country": "Local"
  },
  {
    "time": 1777804119.084065,
    "visitor_id": "1cae6bb3-bcd3-4242-9266-0b870288e609",
    "country": "Local"
  },
  {
    "time": 1777804165.639503,
    "visitor_id": "1cae6bb3-bcd3-4242-9266-0b870288e609",
    "country": "Local"
  },
  {
    "time": 1777804319.1468532,
    "visitor_id": "1cae6bb3-bcd3-4242-9266-0b870288e609",
    "country": "Local"
  },
  {
    "time": 1777804398.5149791,
    "visitor_id": "1cae6bb3-bcd3-4242-9266-0b870288e609",
    "country": "Local"
  },
  {
    "time": 1777805819.1397288,
    "visitor_id": "1cae6bb3-bcd3-4242-9266-0b870288e609",
    "country": "Local"
  },
  {
    "time": 1777805841.1919968,
    "visitor_id": "1cae6bb3-bcd3-4242-9266-0b870288e609",
    "country": "Local"
  },
  {
    "time": 1777806270.709734,
    "visitor_id": "1cae6bb3-bcd3-4242-9266-0b870288e609",
    "country": "Local"
  },
  {
    "time": 1777806736.12169,
    "visitor_id": "1cae6bb3-bcd3-4242-9266-0b870288e609",
    "country": "Local"
  },
  {
    "time": 1777806762.347436,
    "visitor_id": "1cae6bb3-bcd3-4242-9266-0b870288e609",
    "country": "Local"
  },
  {
    "time": 1777807721.738307,
    "visitor_id": "1cae6bb3-bcd3-4242-9266-0b870288e609",
    "country": "Local"
  },
  {
    "time": 1777808395.415953,
    "visitor_id": "1cae6bb3-bcd3-4242-9266-0b870288e609",
    "country": "Local"
  },
  {
    "time": 1777808400.079694,
    "visitor_id": "1cae6bb3-bcd3-4242-9266-0b870288e609",
    "country": "Local"
  },
  {
    "time": 1777809104.766432,
    "visitor_id": "1cae6bb3-bcd3-4242-9266-0b870288e609",
    "country": "Local"
  },
  {
    "time": 1777809228.5701811,
    "visitor_id": "1cae6bb3-bcd3-4242-9266-0b870288e609",
    "country": "Local"
  },
  {
    "time": 1777809817.3387,
    "visitor_id": "1cae6bb3-bcd3-4242-9266-0b870288e609",
    "country": "Local"
  },
  {
    "time": 1777809832.787806,
    "visitor_id": "1cae6bb3-bcd3-4242-9266-0b870288e609",
    "country": "Local"
  },
  {
    "time": 1777809867.2657778,
    "visitor_id": "1cae6bb3-bcd3-4242-9266-0b870288e609",
    "country": "Local"
  },
  {
    "time": 1777810132.838262,
    "visitor_id": "1cae6bb3-bcd3-4242-9266-0b870288e609",
    "country": "Local"
  },
  {
    "time": 1777810147.837627,
    "visitor_id": "1cae6bb3-bcd3-4242-9266-0b870288e609",
    "country": "Local"
  },
  {
    "time": 1777810167.084642,
    "visitor_id": "1cae6bb3-bcd3-4242-9266-0b870288e609",
    "country": "Local"
  },
  {
    "time": 1777810211.717391,
    "visitor_id": "1cae6bb3-bcd3-4242-9266-0b870288e609",
    "country": "Local"
  },
  {
    "time": 1777810267.284323,
    "visitor_id": "1cae6bb3-bcd3-4242-9266-0b870288e609",
    "country": "Local"
  },
  {
    "time": 1777810695.5365329,
    "visitor_id": "1cae6bb3-bcd3-4242-9266-0b870288e609",
    "country": "Local"
  },
  {
    "time": 1777810704.691073,
    "visitor_id": "1cae6bb3-bcd3-4242-9266-0b870288e609",
    "country": "Local"
  },
  {
    "time": 1777810902.0364978,
    "visitor_id": "1cae6bb3-bcd3-4242-9266-0b870288e609",
    "country": "Local"
  },
  {
    "time": 1777810903.856674,
    "visitor_id": "1cae6bb3-bcd3-4242-9266-0b870288e609",
    "country": "Local"
  },
  {
    "time": 1777810905.285551,
    "visitor_id": "1cae6bb3-bcd3-4242-9266-0b870288e609",
    "country": "Local"
  },
  {
    "time": 1777811233.292793,
    "visitor_id": "1cae6bb3-bcd3-4242-9266-0b870288e609",
    "country": "Local"
  },
  {
    "time": 1777811722.252843,
    "visitor_id": "1cae6bb3-bcd3-4242-9266-0b870288e609",
    "country": "Local"
  },
  {
    "time": 1777888815.608854,
    "visitor_id": "dd065251-06d9-4b7f-9013-914470feec6b",
    "country": "Local"
  },
  {
    "time": 1777888827.122792,
    "visitor_id": "dd065251-06d9-4b7f-9013-914470feec6b",
    "country": "Local"
  },
  {
    "time": 1777889501.96337,
    "visitor_id": "1cae6bb3-bcd3-4242-9266-0b870288e609",
    "country": "Local"
  },
  {
    "time": 1777978076.6341178,
    "visitor_id": "1cae6bb3-bcd3-4242-9266-0b870288e609",
    "country": "Local"
  },
  {
    "time": 1777978376.7972941,
    "visitor_id": "1cae6bb3-bcd3-4242-9266-0b870288e609",
    "country": "Local"
  },
  {
    "time": 1777979158.54585,
    "visitor_id": "1cae6bb3-bcd3-4242-9266-0b870288e609",
    "country": "Local"
  },
  {
    "time": 1777979468.865686,
    "visitor_id": "1cae6bb3-bcd3-4242-9266-0b870288e609",
    "country": "Local"
  },
  {
    "time": 1777979526.5405629,
    "visitor_id": "1cae6bb3-bcd3-4242-9266-0b870288e609",
    "country": "Local"
  },
  {
    "time": 1777979620.052274,
    "visitor_id": "1cae6bb3-bcd3-4242-9266-0b870288e609",
    "country": "Local"
  },
  {
    "time": 1777979783.0700102,
    "visitor_id": "1cae6bb3-bcd3-4242-9266-0b870288e609",
    "country": "Local"
  },
  {
    "time": 1777979853.121168,
    "visitor_id": "1cae6bb3-bcd3-4242-9266-0b870288e609",
    "country": "Local"
  },
  {
    "time": 1777979857.353854,
    "visitor_id": "1cae6bb3-bcd3-4242-9266-0b870288e609",
    "country": "Local"
  },
  {
    "time": 1777982220.431509,
    "visitor_id": "1cae6bb3-bcd3-4242-9266-0b870288e609",
    "country": "Local"
  },
  {
    "time": 1778049721.786446,
    "visitor_id": "1cae6bb3-bcd3-4242-9266-0b870288e609",
    "country": "Local"
  },
  {
    "time": 1778049998.658614,
    "visitor_id": "1cae6bb3-bcd3-4242-9266-0b870288e609",
    "country": "Local"
  },
  {
    "time": 1778050096.861475,
    "visitor_id": "1cae6bb3-bcd3-4242-9266-0b870288e609",
    "country": "Local"
  },
  {
    "time": 1778051374.761156,
    "visitor_id": "1cae6bb3-bcd3-4242-9266-0b870288e609",
    "country": "Local"
  },
  {
    "time": 1778051422.241876,
    "visitor_id": "1cae6bb3-bcd3-4242-9266-0b870288e609",
    "country": "Local"
  },
  {
    "time": 1778051568.772398,
    "visitor_id": "1cae6bb3-bcd3-4242-9266-0b870288e609",
    "country": "Local"
  },
  {
    "time": 1778051577.265245,
    "visitor_id": "1cae6bb3-bcd3-4242-9266-0b870288e609",
    "country": "Local"
  },
  {
    "time": 1778051578.6562529,
    "visitor_id": "1cae6bb3-bcd3-4242-9266-0b870288e609",
    "country": "Local"
  },
  {
    "time": 1778051620.509612,
    "visitor_id": "1cae6bb3-bcd3-4242-9266-0b870288e609",
    "country": "Local"
  },
  {
    "time": 1778051633.0872588,
    "visitor_id": "1cae6bb3-bcd3-4242-9266-0b870288e609",
    "country": "Local"
  },
  {
    "time": 1778052042.699244,
    "visitor_id": "1cae6bb3-bcd3-4242-9266-0b870288e609",
    "country": "Local"
  },
  {
    "time": 1778052065.290962,
    "visitor_id": "1cae6bb3-bcd3-4242-9266-0b870288e609",
    "country": "Local"
  },
  {
    "time": 1778052803.113434,
    "visitor_id": "1cae6bb3-bcd3-4242-9266-0b870288e609",
    "country": "Local"
  },
  {
    "time": 1778053596.374742,
    "visitor_id": "1cae6bb3-bcd3-4242-9266-0b870288e609",
    "country": "Local"
  },
  {
    "time": 1778090249.9605162,
    "visitor_id": "1cae6bb3-bcd3-4242-9266-0b870288e609",
    "country": "Local"
  },
  {
    "time": 1778090736.242837,
    "visitor_id": "1cae6bb3-bcd3-4242-9266-0b870288e609",
    "country": "Local"
  },
  {
    "time": 1778094756.6488729,
    "visitor_id": "1cae6bb3-bcd3-4242-9266-0b870288e609",
    "country": "Local"
  },
  {
    "time": 1778096398.949837,
    "visitor_id": "1cae6bb3-bcd3-4242-9266-0b870288e609",
    "country": "Local"
  },
  {
    "time": 1778096485.67649,
    "visitor_id": "1cae6bb3-bcd3-4242-9266-0b870288e609",
    "country": "Local"
  },
  {
    "time": 1778096853.847001,
    "visitor_id": "1cae6bb3-bcd3-4242-9266-0b870288e609",
    "country": "Local"
  },
  {
    "time": 1778140790.950559,
    "visitor_id": "1cae6bb3-bcd3-4242-9266-0b870288e609",
    "country": "Local"
  },
  {
    "time": 1778141722.5372438,
    "visitor_id": "1cae6bb3-bcd3-4242-9266-0b870288e609",
    "country": "Local"
  },
  {
    "time": 1778142534.356907,
    "visitor_id": "1cae6bb3-bcd3-4242-9266-0b870288e609",
    "country": "Local"
  },
  {
    "time": 1778144757.091977,
    "visitor_id": "1cae6bb3-bcd3-4242-9266-0b870288e609",
    "country": "Local"
  },
  {
    "time": 1778145317.1554,
    "visitor_id": "1cae6bb3-bcd3-4242-9266-0b870288e609",
    "country": "Local"
  },
  {
    "time": 1778146221.3197088,
    "visitor_id": "1cae6bb3-bcd3-4242-9266-0b870288e609",
    "country": "Local"
  },
  {
    "time": 1778146325.76625,
    "visitor_id": "1cae6bb3-bcd3-4242-9266-0b870288e609",
    "country": "Local"
  },
  {
    "time": 1778146431.1188211,
    "visitor_id": "1cae6bb3-bcd3-4242-9266-0b870288e609",
    "country": "Local"
  },
  {
    "time": 1778146432.726687,
    "visitor_id": "1cae6bb3-bcd3-4242-9266-0b870288e609",
    "country": "Local"
  },
  {
    "time": 1778146472.723231,
    "visitor_id": "1cae6bb3-bcd3-4242-9266-0b870288e609",
    "country": "Local"
  },
  {
    "time": 1778146726.279881,
    "visitor_id": "1cae6bb3-bcd3-4242-9266-0b870288e609",
    "country": "Local"
  },
  {
    "time": 1778147797.967368,
    "visitor_id": "1cae6bb3-bcd3-4242-9266-0b870288e609",
    "country": "Local"
  },
  {
    "time": 1778148312.892748,
    "visitor_id": "1cae6bb3-bcd3-4242-9266-0b870288e609",
    "country": "Local"
  },
  {
    "time": 1778148770.8381052,
    "visitor_id": "1cae6bb3-bcd3-4242-9266-0b870288e609",
    "country": "Local"
  },
  {
    "time": 1778149131.095764,
    "visitor_id": "1cae6bb3-bcd3-4242-9266-0b870288e609",
    "country": "Local"
  },
  {
    "time": 1778149432.5047958,
    "visitor_id": "1cae6bb3-bcd3-4242-9266-0b870288e609",
    "country": "Local"
  },
  {
    "time": 1778149740.685923,
    "visitor_id": "1cae6bb3-bcd3-4242-9266-0b870288e609",
    "country": "Local"
  },
  {
    "time": 1778150237.707058,
    "visitor_id": "1cae6bb3-bcd3-4242-9266-0b870288e609",
    "country": "Local"
  },
  {
    "time": 1778150848.629524,
    "visitor_id": "1cae6bb3-bcd3-4242-9266-0b870288e609",
    "country": "Local"
  },
  {
    "time": 1778151351.712491,
    "visitor_id": "1cae6bb3-bcd3-4242-9266-0b870288e609",
    "country": "Local"
  },
  {
    "time": 1778151657.269374,
    "visitor_id": "1cae6bb3-bcd3-4242-9266-0b870288e609",
    "country": "Local"
  },
  {
    "time": 1778151986.162026,
    "visitor_id": "1cae6bb3-bcd3-4242-9266-0b870288e609",
    "country": "Local"
  },
  {
    "time": 1778152204.832833,
    "visitor_id": "1cae6bb3-bcd3-4242-9266-0b870288e609",
    "country": "Local"
  },
  {
    "time": 1778153082.075074,
    "visitor_id": "1cae6bb3-bcd3-4242-9266-0b870288e609",
    "country": "Local"
  },
  {
    "time": 1778153102.242368,
    "visitor_id": "1cae6bb3-bcd3-4242-9266-0b870288e609",
    "country": "Local"
  },
  {
    "time": 1778153214.690422,
    "visitor_id": "1cae6bb3-bcd3-4242-9266-0b870288e609",
    "country": "Local"
  },
  {
    "time": 1778153234.3425012,
    "visitor_id": "1cae6bb3-bcd3-4242-9266-0b870288e609",
    "country": "Local"
  },
  {
    "time": 1778170862.9981172,
    "visitor_id": "1cae6bb3-bcd3-4242-9266-0b870288e609",
    "country": "Local"
  },
  {
    "time": 1778170868.588303,
    "visitor_id": "1cae6bb3-bcd3-4242-9266-0b870288e609",
    "country": "Local"
  },
  {
    "time": 1778171412.67731,
    "visitor_id": "1cae6bb3-bcd3-4242-9266-0b870288e609",
    "country": "Local"
  },
  {
    "time": 1778171423.046405,
    "visitor_id": "1cae6bb3-bcd3-4242-9266-0b870288e609",
    "country": "Local"
  },
  {
    "time": 1778172319.629206,
    "visitor_id": "1cae6bb3-bcd3-4242-9266-0b870288e609",
    "country": "Local"
  },
  {
    "time": 1778172403.20941,
    "visitor_id": "1cae6bb3-bcd3-4242-9266-0b870288e609",
    "country": "Local"
  },
  {
    "time": 1778172686.4135768,
    "visitor_id": "1cae6bb3-bcd3-4242-9266-0b870288e609",
    "country": "Local"
  },
  {
    "time": 1778172719.314723,
    "visitor_id": "1cae6bb3-bcd3-4242-9266-0b870288e609",
    "country": "Local"
  },
  {
    "time": 1778173270.511074,
    "visitor_id": "1cae6bb3-bcd3-4242-9266-0b870288e609",
    "country": "Local"
  },
  {
    "time": 1778173283.490984,
    "visitor_id": "1cae6bb3-bcd3-4242-9266-0b870288e609",
    "country": "Local"
  },
  {
    "time": 1778173444.138944,
    "visitor_id": "1cae6bb3-bcd3-4242-9266-0b870288e609",
    "country": "Local"
  },
  {
    "time": 1778173622.164326,
    "visitor_id": "1cae6bb3-bcd3-4242-9266-0b870288e609",
    "country": "Local"
  },
  {
    "time": 1778173653.462959,
    "visitor_id": "1cae6bb3-bcd3-4242-9266-0b870288e609",
    "country": "Local"
  },
  {
    "time": 1778173791.363091,
    "visitor_id": "1cae6bb3-bcd3-4242-9266-0b870288e609",
    "country": "Local"
  },
  {
    "time": 1778173814.374146,
    "visitor_id": "1cae6bb3-bcd3-4242-9266-0b870288e609",
    "country": "Local"
  },
  {
    "time": 1778174013.5934331,
    "visitor_id": "1cae6bb3-bcd3-4242-9266-0b870288e609",
    "country": "Local"
  },
  {
    "time": 1778174277.562877,
    "visitor_id": "1cae6bb3-bcd3-4242-9266-0b870288e609",
    "country": "Local"
  },
  {
    "time": 1778174603.059984,
    "visitor_id": "1cae6bb3-bcd3-4242-9266-0b870288e609",
    "country": "Local"
  },
  {
    "time": 1778174928.860051,
    "visitor_id": "1cae6bb3-bcd3-4242-9266-0b870288e609",
    "country": "Local"
  },
  {
    "time": 1778175390.655359,
    "visitor_id": "1cae6bb3-bcd3-4242-9266-0b870288e609",
    "country": "Local"
  },
  {
    "time": 1778176281.051022,
    "visitor_id": "1cae6bb3-bcd3-4242-9266-0b870288e609",
    "country": "Local"
  },
  {
    "time": 1778176418.998646,
    "visitor_id": "1cae6bb3-bcd3-4242-9266-0b870288e609",
    "country": "Local"
  },
  {
    "time": 1778176897.035053,
    "visitor_id": "1cae6bb3-bcd3-4242-9266-0b870288e609",
    "country": "Local"
  },
  {
    "time": 1778177916.3989508,
    "visitor_id": "1cae6bb3-bcd3-4242-9266-0b870288e609",
    "country": "Local"
  },
  {
    "time": 1778179935.367732,
    "visitor_id": "1cae6bb3-bcd3-4242-9266-0b870288e609",
    "country": "Local"
  },
  {
    "time": 1778180017.258102,
    "visitor_id": "1cae6bb3-bcd3-4242-9266-0b870288e609",
    "country": "Local"
  },
  {
    "time": 1778180115.065855,
    "visitor_id": "1cae6bb3-bcd3-4242-9266-0b870288e609",
    "country": "Local"
  },
  {
    "time": 1778180123.638879,
    "visitor_id": "1cae6bb3-bcd3-4242-9266-0b870288e609",
    "country": "Local"
  },
  {
    "time": 1778180397.7886589,
    "visitor_id": "1cae6bb3-bcd3-4242-9266-0b870288e609",
    "country": "Local"
  },
  {
    "time": 1778180502.296157,
    "visitor_id": "1cae6bb3-bcd3-4242-9266-0b870288e609",
    "country": "Local"
  },
  {
    "time": 1778180966.620169,
    "visitor_id": "1cae6bb3-bcd3-4242-9266-0b870288e609",
    "country": "Local"
  },
  {
    "time": 1778181161.2067058,
    "visitor_id": "1cae6bb3-bcd3-4242-9266-0b870288e609",
    "country": "Local"
  },
  {
    "time": 1778229767.41939,
    "visitor_id": "1cae6bb3-bcd3-4242-9266-0b870288e609",
    "country": "Local"
  },
  {
    "time": 1778231228.0714371,
    "visitor_id": "1cae6bb3-bcd3-4242-9266-0b870288e609",
    "country": "Local"
  },
  {
    "time": 1778231716.917386,
    "visitor_id": "1cae6bb3-bcd3-4242-9266-0b870288e609",
    "country": "Local"
  },
  {
    "time": 1778232509.043992,
    "visitor_id": "1cae6bb3-bcd3-4242-9266-0b870288e609",
    "country": "Local"
  },
  {
    "time": 1778232852.257014,
    "visitor_id": "1cae6bb3-bcd3-4242-9266-0b870288e609",
    "country": "Local"
  },
  {
    "time": 1778233301.654068,
    "visitor_id": "1cae6bb3-bcd3-4242-9266-0b870288e609",
    "country": "Local"
  },
  {
    "time": 1778234231.7879,
    "visitor_id": "1cae6bb3-bcd3-4242-9266-0b870288e609",
    "country": "Local"
  },
  {
    "time": 1778236210.280648,
    "visitor_id": "1cae6bb3-bcd3-4242-9266-0b870288e609",
    "country": "Local"
  },
  {
    "time": 1778259721.05952,
    "visitor_id": "1cae6bb3-bcd3-4242-9266-0b870288e609",
    "country": "Local"
  },
  {
    "time": 1778261428.599353,
    "visitor_id": "1cae6bb3-bcd3-4242-9266-0b870288e609",
    "country": "Local"
  },
  {
    "time": 1778261741.474972,
    "visitor_id": "1cae6bb3-bcd3-4242-9266-0b870288e609",
    "country": "Local"
  },
  {
    "time": 1778262236.4248488,
    "visitor_id": "1cae6bb3-bcd3-4242-9266-0b870288e609",
    "country": "Local"
  },
  {
    "time": 1778262262.7068532,
    "visitor_id": "1cae6bb3-bcd3-4242-9266-0b870288e609",
    "country": "Local"
  },
  {
    "time": 1778492208.151829,
    "visitor_id": "1cae6bb3-bcd3-4242-9266-0b870288e609",
    "country": "Local"
  },
  {
    "time": 1778492728.1342442,
    "visitor_id": "1cae6bb3-bcd3-4242-9266-0b870288e609",
    "country": "Local"
  },
  {
    "time": 1778493473.6389818,
    "visitor_id": "1cae6bb3-bcd3-4242-9266-0b870288e609",
    "country": "Local"
  },
  {
    "time": 1778493612.221259,
    "visitor_id": "1cae6bb3-bcd3-4242-9266-0b870288e609",
    "country": "Local"
  },
  {
    "time": 1778493863.903476,
    "visitor_id": "1cae6bb3-bcd3-4242-9266-0b870288e609",
    "country": "Local"
  },
  {
    "time": 1778493880.7899241,
    "visitor_id": "1cae6bb3-bcd3-4242-9266-0b870288e609",
    "country": "Local"
  },
  {
    "time": 1778494937.439095,
    "visitor_id": "1cae6bb3-bcd3-4242-9266-0b870288e609",
    "country": "Local"
  },
  {
    "time": 1778495619.435551,
    "visitor_id": "1cae6bb3-bcd3-4242-9266-0b870288e609",
    "country": "Local"
  },
  {
    "time": 1778496505.1075919,
    "visitor_id": "1cae6bb3-bcd3-4242-9266-0b870288e609",
    "country": "Local"
  },
  {
    "time": 1778497586.455654,
    "visitor_id": "1cae6bb3-bcd3-4242-9266-0b870288e609",
    "country": "Local"
  },
  {
    "time": 1778497907.0048,
    "visitor_id": "1cae6bb3-bcd3-4242-9266-0b870288e609",
    "country": "Local"
  },
  {
    "time": 1778498308.978812,
    "visitor_id": "1cae6bb3-bcd3-4242-9266-0b870288e609",
    "country": "Local"
  },
  {
    "time": 1778498746.3415942,
    "visitor_id": "1cae6bb3-bcd3-4242-9266-0b870288e609",
    "country": "Local"
  },
  {
    "time": 1778498770.1353889,
    "visitor_id": "1cae6bb3-bcd3-4242-9266-0b870288e609",
    "country": "Local"
  },
  {
    "time": 1778499743.907647,
    "visitor_id": "1cae6bb3-bcd3-4242-9266-0b870288e609",
    "country": "Local"
  },
  {
    "time": 1778499827.467842,
    "visitor_id": "1cae6bb3-bcd3-4242-9266-0b870288e609",
    "country": "Local"
  },
  {
    "time": 1778500721.880933,
    "visitor_id": "1cae6bb3-bcd3-4242-9266-0b870288e609",
    "country": "Local"
  },
  {
    "time": 1778502409.582176,
    "visitor_id": "1cae6bb3-bcd3-4242-9266-0b870288e609",
    "country": "Local"
  },
  {
    "time": 1778502591.05039,
    "visitor_id": "1cae6bb3-bcd3-4242-9266-0b870288e609",
    "country": "Local"
  },
  {
    "time": 1778502944.735996,
    "visitor_id": "1cae6bb3-bcd3-4242-9266-0b870288e609",
    "country": "Local"
  },
  {
    "time": 1778502965.254055,
    "visitor_id": "1cae6bb3-bcd3-4242-9266-0b870288e609",
    "country": "Local"
  },
  {
    "time": 1778503224.083039,
    "visitor_id": "1cae6bb3-bcd3-4242-9266-0b870288e609",
    "country": "Local"
  },
  {
    "time": 1778504045.8632991,
    "visitor_id": "1cae6bb3-bcd3-4242-9266-0b870288e609",
    "country": "Local"
  },
  {
    "time": 1778504134.9630919,
    "visitor_id": "1cae6bb3-bcd3-4242-9266-0b870288e609",
    "country": "Local"
  },
  {
    "time": 1778504231.005595,
    "visitor_id": "1cae6bb3-bcd3-4242-9266-0b870288e609",
    "country": "Local"
  },
  {
    "time": 1778504708.054226,
    "visitor_id": "1cae6bb3-bcd3-4242-9266-0b870288e609",
    "country": "Local"
  },
  {
    "time": 1778505037.840242,
    "visitor_id": "1cae6bb3-bcd3-4242-9266-0b870288e609",
    "country": "Local"
  },
  {
    "time": 1778505889.052693,
    "visitor_id": "1cae6bb3-bcd3-4242-9266-0b870288e609",
    "country": "Local"
  },
  {
    "time": 1778506540.901242,
    "visitor_id": "1cae6bb3-bcd3-4242-9266-0b870288e609",
    "country": "Local"
  },
  {
    "time": 1778507324.201438,
    "visitor_id": "1cae6bb3-bcd3-4242-9266-0b870288e609",
    "country": "Local"
  },
  {
    "time": 1778509390.3883011,
    "visitor_id": "1cae6bb3-bcd3-4242-9266-0b870288e609",
    "country": "Local"
  },
  {
    "time": 1778510466.367766,
    "visitor_id": "1cae6bb3-bcd3-4242-9266-0b870288e609",
    "country": "Local"
  },
  {
    "time": 1778510914.566507,
    "visitor_id": "1cae6bb3-bcd3-4242-9266-0b870288e609",
    "country": "Local"
  },
  {
    "time": 1778511690.5123541,
    "visitor_id": "1cae6bb3-bcd3-4242-9266-0b870288e609",
    "country": "Local"
  },
  {
    "time": 1778512372.505195,
    "visitor_id": "1cae6bb3-bcd3-4242-9266-0b870288e609",
    "country": "Local"
  },
  {
    "time": 1778512394.1192589,
    "visitor_id": "1cae6bb3-bcd3-4242-9266-0b870288e609",
    "country": "Local"
  },
  {
    "time": 1778512808.0827498,
    "visitor_id": "1cae6bb3-bcd3-4242-9266-0b870288e609",
    "country": "Local"
  },
  {
    "time": 1778512824.566776,
    "visitor_id": "1cae6bb3-bcd3-4242-9266-0b870288e609",
    "country": "Local"
  },
  {
    "time": 1778513160.731888,
    "visitor_id": "1cae6bb3-bcd3-4242-9266-0b870288e609",
    "country": "Local"
  },
  {
    "time": 1778543426.785472,
    "visitor_id": "1cae6bb3-bcd3-4242-9266-0b870288e609",
    "country": "Local"
  },
  {
    "time": 1778551994.424932,
    "visitor_id": "1cae6bb3-bcd3-4242-9266-0b870288e609",
    "country": "Local"
  },
  {
    "time": 1778554501.741982,
    "visitor_id": "1cae6bb3-bcd3-4242-9266-0b870288e609",
    "country": "Local"
  },
  {
    "time": 1778617768.733577,
    "visitor_id": "1cae6bb3-bcd3-4242-9266-0b870288e609",
    "country": "Local"
  },
  {
    "time": 1778618083.458721,
    "visitor_id": "1cae6bb3-bcd3-4242-9266-0b870288e609",
    "country": "Local"
  },
  {
    "time": 1778619292.929096,
    "visitor_id": "1cae6bb3-bcd3-4242-9266-0b870288e609",
    "country": "Local"
  },
  {
    "time": 1778619299.101763,
    "visitor_id": "1cae6bb3-bcd3-4242-9266-0b870288e609",
    "country": "Local"
  },
  {
    "time": 1778619673.985333,
    "visitor_id": "1cae6bb3-bcd3-4242-9266-0b870288e609",
    "country": "Local"
  },
  {
    "time": 1778619846.281919,
    "visitor_id": "1cae6bb3-bcd3-4242-9266-0b870288e609",
    "country": "Local"
  },
  {
    "time": 1778619961.525552,
    "visitor_id": "1cae6bb3-bcd3-4242-9266-0b870288e609",
    "country": "Local"
  },
  {
    "time": 1778619984.134559,
    "visitor_id": "1cae6bb3-bcd3-4242-9266-0b870288e609",
    "country": "Local"
  },
  {
    "time": 1778620234.997751,
    "visitor_id": "1cae6bb3-bcd3-4242-9266-0b870288e609",
    "country": "Local"
  },
  {
    "time": 1778622053.229789,
    "visitor_id": "1cae6bb3-bcd3-4242-9266-0b870288e609",
    "country": "Local"
  },
  {
    "time": 1778622349.348097,
    "visitor_id": "1cae6bb3-bcd3-4242-9266-0b870288e609",
    "country": "Local"
  },
  {
    "time": 1778637928.0927072,
    "visitor_id": "1cae6bb3-bcd3-4242-9266-0b870288e609",
    "country": "Local"
  },
  {
    "time": 1778638319.182295,
    "visitor_id": "1cae6bb3-bcd3-4242-9266-0b870288e609",
    "country": "Local"
  },
  {
    "time": 1778670017.453542,
    "visitor_id": "1cae6bb3-bcd3-4242-9266-0b870288e609",
    "country": "Local"
  },
  {
    "time": 1778696919.565312,
    "visitor_id": "1cae6bb3-bcd3-4242-9266-0b870288e609",
    "country": "Local"
  },
  {
    "time": 1778698080.066025,
    "visitor_id": "1cae6bb3-bcd3-4242-9266-0b870288e609",
    "country": "Local"
  },
  {
    "time": 1778698098.236628,
    "visitor_id": "1cae6bb3-bcd3-4242-9266-0b870288e609",
    "country": "Local"
  },
  {
    "time": 1778703751.294938,
    "visitor_id": "1cae6bb3-bcd3-4242-9266-0b870288e609",
    "country": "Local"
  },
  {
    "time": 1778705452.0354738,
    "visitor_id": "1cae6bb3-bcd3-4242-9266-0b870288e609",
    "country": "Local"
  },
  {
    "time": 1778706071.2556338,
    "visitor_id": "1cae6bb3-bcd3-4242-9266-0b870288e609",
    "country": "Local"
  },
  {
    "time": 1778709293.758837,
    "visitor_id": "1cae6bb3-bcd3-4242-9266-0b870288e609",
    "country": "Local"
  },
  {
    "time": 1778712671.5452318,
    "visitor_id": "1cae6bb3-bcd3-4242-9266-0b870288e609",
    "country": "Local"
  },
  {
    "time": 1778712901.6860642,
    "visitor_id": "1cae6bb3-bcd3-4242-9266-0b870288e609",
    "country": "Local"
  },
  {
    "time": 1778713064.380963,
    "visitor_id": "1cae6bb3-bcd3-4242-9266-0b870288e609",
    "country": "Local"
  },
  {
    "time": 1778713188.6331,
    "visitor_id": "1cae6bb3-bcd3-4242-9266-0b870288e609",
    "country": "Local"
  },
  {
    "time": 1778713302.107212,
    "visitor_id": "1cae6bb3-bcd3-4242-9266-0b870288e609",
    "country": "Local"
  },
  {
    "time": 1778843307.3467698,
    "visitor_id": "1cae6bb3-bcd3-4242-9266-0b870288e609",
    "country": "Local"
  },
  {
    "time": 1778843796.208677,
    "visitor_id": "1cae6bb3-bcd3-4242-9266-0b870288e609",
    "country": "Local"
  },
  {
    "time": 1778844375.0000908,
    "visitor_id": "1cae6bb3-bcd3-4242-9266-0b870288e609",
    "country": "Local"
  },
  {
    "time": 1778844402.774029,
    "visitor_id": "1cae6bb3-bcd3-4242-9266-0b870288e609",
    "country": "Local"
  },
  {
    "time": 1778844428.23442,
    "visitor_id": "1cae6bb3-bcd3-4242-9266-0b870288e609",
    "country": "Local"
  },
  {
    "time": 1778845231.2679732,
    "visitor_id": "1cae6bb3-bcd3-4242-9266-0b870288e609",
    "country": "Local"
  },
  {
    "time": 1778866516.3117352,
    "visitor_id": "1cae6bb3-bcd3-4242-9266-0b870288e609",
    "country": "Local"
  },
  {
    "time": 1778876894.2142,
    "visitor_id": "1cae6bb3-bcd3-4242-9266-0b870288e609",
    "country": "Local"
  },
  {
    "time": 1778878955.930897,
    "visitor_id": "1cae6bb3-bcd3-4242-9266-0b870288e609",
    "country": "Local"
  },
  {
    "time": 1778879279.660652,
    "visitor_id": "1cae6bb3-bcd3-4242-9266-0b870288e609",
    "country": "Local"
  },
  {
    "time": 1778879280.7680829,
    "visitor_id": "1cae6bb3-bcd3-4242-9266-0b870288e609",
    "country": "Local"
  },
  {
    "time": 1778945041.079802,
    "visitor_id": "1cae6bb3-bcd3-4242-9266-0b870288e609",
    "country": "Local"
  },
  {
    "time": 1778946099.837091,
    "visitor_id": "1cae6bb3-bcd3-4242-9266-0b870288e609",
    "country": "Local"
  },
  {
    "time": 1778946108.38867,
    "visitor_id": "1cae6bb3-bcd3-4242-9266-0b870288e609",
    "country": "Local"
  },
  {
    "time": 1778946457.636086,
    "visitor_id": "1cae6bb3-bcd3-4242-9266-0b870288e609",
    "country": "Local"
  },
  {
    "time": 1778947122.36204,
    "visitor_id": "1cae6bb3-bcd3-4242-9266-0b870288e609",
    "country": "Local"
  },
  {
    "time": 1778947301.913913,
    "visitor_id": "1cae6bb3-bcd3-4242-9266-0b870288e609",
    "country": "Local"
  },
  {
    "time": 1778948185.3317702,
    "visitor_id": "1cae6bb3-bcd3-4242-9266-0b870288e609",
    "country": "Local"
  },
  {
    "time": 1778948724.3448231,
    "visitor_id": "1cae6bb3-bcd3-4242-9266-0b870288e609",
    "country": "Local"
  },
  {
    "time": 1778948842.509038,
    "visitor_id": "1cae6bb3-bcd3-4242-9266-0b870288e609",
    "country": "Local"
  },
  {
    "time": 1778948929.850948,
    "visitor_id": "1cae6bb3-bcd3-4242-9266-0b870288e609",
    "country": "Local"
  },
  {
    "time": 1778948944.389576,
    "visitor_id": "1cae6bb3-bcd3-4242-9266-0b870288e609",
    "country": "Local"
  },
  {
    "time": 1778949053.6427891,
    "visitor_id": "1cae6bb3-bcd3-4242-9266-0b870288e609",
    "country": "Local"
  },
  {
    "time": 1778949956.504098,
    "visitor_id": "1cae6bb3-bcd3-4242-9266-0b870288e609",
    "country": "Local"
  },
  {
    "time": 1778949989.56937,
    "visitor_id": "1cae6bb3-bcd3-4242-9266-0b870288e609",
    "country": "Local"
  },
  {
    "time": 1778950036.057423,
    "visitor_id": "1cae6bb3-bcd3-4242-9266-0b870288e609",
    "country": "Local"
  },
  {
    "time": 1778976934.7876549,
    "visitor_id": "1cae6bb3-bcd3-4242-9266-0b870288e609",
    "country": "Local"
  },
  {
    "time": 1778977547.448715,
    "visitor_id": "1cae6bb3-bcd3-4242-9266-0b870288e609",
    "country": "Local"
  },
  {
    "time": 1778977591.07695,
    "visitor_id": "1cae6bb3-bcd3-4242-9266-0b870288e609",
    "country": "Local"
  },
  {
    "time": 1778978247.3126998,
    "visitor_id": "1cae6bb3-bcd3-4242-9266-0b870288e609",
    "country": "Local"
  },
  {
    "time": 1778978533.765037,
    "visitor_id": "1cae6bb3-bcd3-4242-9266-0b870288e609",
    "country": "Local"
  },
  {
    "time": 1778978574.020545,
    "visitor_id": "1cae6bb3-bcd3-4242-9266-0b870288e609",
    "country": "Local"
  },
  {
    "time": 1778978782.841283,
    "visitor_id": "1cae6bb3-bcd3-4242-9266-0b870288e609",
    "country": "Local"
  },
  {
    "time": 1778980299.1148002,
    "visitor_id": "1cae6bb3-bcd3-4242-9266-0b870288e609",
    "country": "Local"
  },
  {
    "time": 1779016450.1913128,
    "visitor_id": "1cae6bb3-bcd3-4242-9266-0b870288e609",
    "country": "Local"
  },
  {
    "time": 1779016457.837719,
    "visitor_id": "1cae6bb3-bcd3-4242-9266-0b870288e609",
    "country": "Local"
  },
  {
    "time": 1779016541.1835341,
    "visitor_id": "1cae6bb3-bcd3-4242-9266-0b870288e609",
    "country": "Local"
  },
  {
    "time": 1779016542.210401,
    "visitor_id": "1cae6bb3-bcd3-4242-9266-0b870288e609",
    "country": "Local"
  },
  {
    "time": 1779016773.599177,
    "visitor_id": "1cae6bb3-bcd3-4242-9266-0b870288e609",
    "country": "Local"
  },
  {
    "time": 1779016788.796418,
    "visitor_id": "1cae6bb3-bcd3-4242-9266-0b870288e609",
    "country": "Local"
  },
  {
    "time": 1779016821.6972601,
    "visitor_id": "1cae6bb3-bcd3-4242-9266-0b870288e609",
    "country": "Local"
  },
  {
    "time": 1779017274.4189708,
    "visitor_id": "1cae6bb3-bcd3-4242-9266-0b870288e609",
    "country": "Local"
  },
  {
    "time": 1779017836.184269,
    "visitor_id": "1cae6bb3-bcd3-4242-9266-0b870288e609",
    "country": "Local"
  },
  {
    "time": 1779017945.525409,
    "visitor_id": "1cae6bb3-bcd3-4242-9266-0b870288e609",
    "country": "Local"
  },
  {
    "time": 1779018099.070108,
    "visitor_id": "1cae6bb3-bcd3-4242-9266-0b870288e609",
    "country": "Local"
  },
  {
    "time": 1779018146.6853938,
    "visitor_id": "1cae6bb3-bcd3-4242-9266-0b870288e609",
    "country": "Local"
  },
  {
    "time": 1779018444.373385,
    "visitor_id": "1cae6bb3-bcd3-4242-9266-0b870288e609",
    "country": "Local"
  },
  {
    "time": 1779018797.7545779,
    "visitor_id": "1cae6bb3-bcd3-4242-9266-0b870288e609",
    "country": "Local"
  },
  {
    "time": 1779019230.521237,
    "visitor_id": "1cae6bb3-bcd3-4242-9266-0b870288e609",
    "country": "Local"
  },
  {
    "time": 1779019248.285651,
    "visitor_id": "1cae6bb3-bcd3-4242-9266-0b870288e609",
    "country": "Local"
  },
  {
    "time": 1779019496.5156531,
    "visitor_id": "1cae6bb3-bcd3-4242-9266-0b870288e609",
    "country": "Local"
  },
  {
    "time": 1779019511.689142,
    "visitor_id": "1cae6bb3-bcd3-4242-9266-0b870288e609",
    "country": "Local"
  },
  {
    "time": 1779019701.156319,
    "visitor_id": "1cae6bb3-bcd3-4242-9266-0b870288e609",
    "country": "Local"
  },
  {
    "time": 1779020342.783547,
    "visitor_id": "1cae6bb3-bcd3-4242-9266-0b870288e609",
    "country": "Local"
  },
  {
    "time": 1779021078.1805792,
    "visitor_id": "1cae6bb3-bcd3-4242-9266-0b870288e609",
    "country": "Local"
  },
  {
    "time": 1779021162.1413062,
    "visitor_id": "1cae6bb3-bcd3-4242-9266-0b870288e609",
    "country": "Local"
  },
  {
    "time": 1779021434.968906,
    "visitor_id": "1cae6bb3-bcd3-4242-9266-0b870288e609",
    "country": "Local"
  },
  {
    "time": 1779021454.874537,
    "visitor_id": "1cae6bb3-bcd3-4242-9266-0b870288e609",
    "country": "Local"
  },
  {
    "time": 1779021460.740143,
    "visitor_id": "1cae6bb3-bcd3-4242-9266-0b870288e609",
    "country": "Local"
  },
  {
    "time": 1779022055.617132,
    "visitor_id": "1cae6bb3-bcd3-4242-9266-0b870288e609",
    "country": "Local"
  },
  {
    "time": 1779022357.800214,
    "visitor_id": "1cae6bb3-bcd3-4242-9266-0b870288e609",
    "country": "Local"
  },
  {
    "time": 1779022360.6367638,
    "visitor_id": "1cae6bb3-bcd3-4242-9266-0b870288e609",
    "country": "Local"
  },
  {
    "time": 1779022942.242271,
    "visitor_id": "1cae6bb3-bcd3-4242-9266-0b870288e609",
    "country": "Local"
  },
  {
    "time": 1779023277.1610901,
    "visitor_id": "1cae6bb3-bcd3-4242-9266-0b870288e609",
    "country": "Local"
  },
  {
    "time": 1779023285.086299,
    "visitor_id": "1cae6bb3-bcd3-4242-9266-0b870288e609",
    "country": "Local"
  },
  {
    "time": 1779023304.763243,
    "visitor_id": "1cae6bb3-bcd3-4242-9266-0b870288e609",
    "country": "Local"
  },
  {
    "time": 1779038480.18281,
    "visitor_id": "1cae6bb3-bcd3-4242-9266-0b870288e609",
    "country": "Local"
  },
  {
    "time": 1779038685.678729,
    "visitor_id": "1cae6bb3-bcd3-4242-9266-0b870288e609",
    "country": "Local"
  },
  {
    "time": 1779038695.0604749,
    "visitor_id": "1cae6bb3-bcd3-4242-9266-0b870288e609",
    "country": "Local"
  },
  {
    "time": 1779039179.523432,
    "visitor_id": "1cae6bb3-bcd3-4242-9266-0b870288e609",
    "country": "Local"
  },
  {
    "time": 1779040203.232563,
    "visitor_id": "1cae6bb3-bcd3-4242-9266-0b870288e609",
    "country": "Local"
  },
  {
    "time": 1779048784.5070982,
    "visitor_id": "1cae6bb3-bcd3-4242-9266-0b870288e609",
    "country": "Local"
  },
  {
    "time": 1779048902.683723,
    "visitor_id": "1cae6bb3-bcd3-4242-9266-0b870288e609",
    "country": "Local"
  },
  {
    "time": 1779049726.705152,
    "visitor_id": "1cae6bb3-bcd3-4242-9266-0b870288e609",
    "country": "Local"
  },
  {
    "time": 1779049903.780915,
    "visitor_id": "1cae6bb3-bcd3-4242-9266-0b870288e609",
    "country": "Local"
  },
  {
    "time": 1779050316.084484,
    "visitor_id": "1cae6bb3-bcd3-4242-9266-0b870288e609",
    "country": "Local"
  },
  {
    "time": 1779050344.270729,
    "visitor_id": "1cae6bb3-bcd3-4242-9266-0b870288e609",
    "country": "Local"
  },
  {
    "time": 1779050355.068894,
    "visitor_id": "1cae6bb3-bcd3-4242-9266-0b870288e609",
    "country": "Local"
  },
  {
    "time": 1779050392.337228,
    "visitor_id": "1cae6bb3-bcd3-4242-9266-0b870288e609",
    "country": "Local"
  },
  {
    "time": 1779050416.7606242,
    "visitor_id": "1cae6bb3-bcd3-4242-9266-0b870288e609",
    "country": "Local"
  },
  {
    "time": 1779050446.2959502,
    "visitor_id": "1cae6bb3-bcd3-4242-9266-0b870288e609",
    "country": "Local"
  },
  {
    "time": 1779050479.063317,
    "visitor_id": "1cae6bb3-bcd3-4242-9266-0b870288e609",
    "country": "Local"
  },
  {
    "time": 1779050487.847121,
    "visitor_id": "1cae6bb3-bcd3-4242-9266-0b870288e609",
    "country": "Local"
  },
  {
    "time": 1779050513.7700381,
    "visitor_id": "1cae6bb3-bcd3-4242-9266-0b870288e609",
    "country": "Local"
  },
  {
    "time": 1779050535.319881,
    "visitor_id": "1cae6bb3-bcd3-4242-9266-0b870288e609",
    "country": "Local"
  },
  {
    "time": 1779050558.590558,
    "visitor_id": "1cae6bb3-bcd3-4242-9266-0b870288e609",
    "country": "Local"
  },
  {
    "time": 1779050580.687676,
    "visitor_id": "1cae6bb3-bcd3-4242-9266-0b870288e609",
    "country": "Local"
  },
  {
    "time": 1779050638.888366,
    "visitor_id": "1cae6bb3-bcd3-4242-9266-0b870288e609",
    "country": "Local"
  },
  {
    "time": 1779050685.703449,
    "visitor_id": "1cae6bb3-bcd3-4242-9266-0b870288e609",
    "country": "Local"
  },
  {
    "time": 1779050727.839217,
    "visitor_id": "1cae6bb3-bcd3-4242-9266-0b870288e609",
    "country": "Local"
  },
  {
    "time": 1779050751.092312,
    "visitor_id": "1cae6bb3-bcd3-4242-9266-0b870288e609",
    "country": "Local"
  },
  {
    "time": 1779050774.951985,
    "visitor_id": "1cae6bb3-bcd3-4242-9266-0b870288e609",
    "country": "Local"
  },
  {
    "time": 1779050790.8733199,
    "visitor_id": "1cae6bb3-bcd3-4242-9266-0b870288e609",
    "country": "Local"
  },
  {
    "time": 1779050809.1316879,
    "visitor_id": "1cae6bb3-bcd3-4242-9266-0b870288e609",
    "country": "Local"
  },
  {
    "time": 1779050832.357216,
    "visitor_id": "1cae6bb3-bcd3-4242-9266-0b870288e609",
    "country": "Local"
  },
  {
    "time": 1779050872.857656,
    "visitor_id": "1cae6bb3-bcd3-4242-9266-0b870288e609",
    "country": "Local"
  },
  {
    "time": 1779050900.047772,
    "visitor_id": "1cae6bb3-bcd3-4242-9266-0b870288e609",
    "country": "Local"
  },
  {
    "time": 1779050939.8561862,
    "visitor_id": "1cae6bb3-bcd3-4242-9266-0b870288e609",
    "country": "Local"
  },
  {
    "time": 1779050958.480339,
    "visitor_id": "1cae6bb3-bcd3-4242-9266-0b870288e609",
    "country": "Local"
  },
  {
    "time": 1779051030.082795,
    "visitor_id": "1cae6bb3-bcd3-4242-9266-0b870288e609",
    "country": "Local"
  },
  {
    "time": 1779051063.204059,
    "visitor_id": "1cae6bb3-bcd3-4242-9266-0b870288e609",
    "country": "Local"
  },
  {
    "time": 1779051125.185944,
    "visitor_id": "1cae6bb3-bcd3-4242-9266-0b870288e609",
    "country": "Local"
  },
  {
    "time": 1779051488.089632,
    "visitor_id": "1cae6bb3-bcd3-4242-9266-0b870288e609",
    "country": "Local"
  },
  {
    "time": 1779051738.972509,
    "visitor_id": "1cae6bb3-bcd3-4242-9266-0b870288e609",
    "country": "Local"
  },
  {
    "time": 1779052089.4937322,
    "visitor_id": "1cae6bb3-bcd3-4242-9266-0b870288e609",
    "country": "Local"
  },
  {
    "time": 1779052225.278375,
    "visitor_id": "1cae6bb3-bcd3-4242-9266-0b870288e609",
    "country": "Local"
  },
  {
    "time": 1779052267.720022,
    "visitor_id": "1cae6bb3-bcd3-4242-9266-0b870288e609",
    "country": "Local"
  },
  {
    "time": 1779052346.860401,
    "visitor_id": "1cae6bb3-bcd3-4242-9266-0b870288e609",
    "country": "Local"
  },
  {
    "time": 1779052417.360654,
    "visitor_id": "1cae6bb3-bcd3-4242-9266-0b870288e609",
    "country": "Local"
  },
  {
    "time": 1779052481.28783,
    "visitor_id": "1cae6bb3-bcd3-4242-9266-0b870288e609",
    "country": "Local"
  },
  {
    "time": 1779052689.4345658,
    "visitor_id": "1cae6bb3-bcd3-4242-9266-0b870288e609",
    "country": "Local"
  },
  {
    "time": 1779052730.485151,
    "visitor_id": "1cae6bb3-bcd3-4242-9266-0b870288e609",
    "country": "Local"
  },
  {
    "time": 1779052781.208766,
    "visitor_id": "1cae6bb3-bcd3-4242-9266-0b870288e609",
    "country": "Local"
  },
  {
    "time": 1779053066.004224,
    "visitor_id": "1cae6bb3-bcd3-4242-9266-0b870288e609",
    "country": "Local"
  },
  {
    "time": 1779053188.4229472,
    "visitor_id": "1cae6bb3-bcd3-4242-9266-0b870288e609",
    "country": "Local"
  },
  {
    "time": 1779053224.284404,
    "visitor_id": "1cae6bb3-bcd3-4242-9266-0b870288e609",
    "country": "Local"
  },
  {
    "time": 1779053249.428279,
    "visitor_id": "1cae6bb3-bcd3-4242-9266-0b870288e609",
    "country": "Local"
  },
  {
    "time": 1779053273.417821,
    "visitor_id": "1cae6bb3-bcd3-4242-9266-0b870288e609",
    "country": "Local"
  },
  {
    "time": 1779053302.6785028,
    "visitor_id": "1cae6bb3-bcd3-4242-9266-0b870288e609",
    "country": "Local"
  },
  {
    "time": 1779053315.669024,
    "visitor_id": "1cae6bb3-bcd3-4242-9266-0b870288e609",
    "country": "Local"
  },
  {
    "time": 1779054506.159073,
    "visitor_id": "1cae6bb3-bcd3-4242-9266-0b870288e609",
    "country": "Local"
  },
  {
    "time": 1779054796.03728,
    "visitor_id": "1cae6bb3-bcd3-4242-9266-0b870288e609",
    "country": "Local"
  },
  {
    "time": 1779056305.6815271,
    "visitor_id": "1cae6bb3-bcd3-4242-9266-0b870288e609",
    "country": "Local"
  },
  {
    "time": 1779056959.0439968,
    "visitor_id": "1cae6bb3-bcd3-4242-9266-0b870288e609",
    "country": "Local"
  },
  {
    "time": 1779060338.634528,
    "visitor_id": "1cae6bb3-bcd3-4242-9266-0b870288e609",
    "country": "Local"
  },
  {
    "time": 1779060591.4783628,
    "visitor_id": "1cae6bb3-bcd3-4242-9266-0b870288e609",
    "country": "Local"
  },
  {
    "time": 1779060639.967468,
    "visitor_id": "1cae6bb3-bcd3-4242-9266-0b870288e609",
    "country": "Local"
  },
  {
    "time": 1779061015.3840482,
    "visitor_id": "1cae6bb3-bcd3-4242-9266-0b870288e609",
    "country": "Local"
  },
  {
    "time": 1779061038.048414,
    "visitor_id": "1cae6bb3-bcd3-4242-9266-0b870288e609",
    "country": "Local"
  },
  {
    "time": 1779061046.530049,
    "visitor_id": "1cae6bb3-bcd3-4242-9266-0b870288e609",
    "country": "Local"
  },
  {
    "time": 1779078355.9182,
    "visitor_id": "1cae6bb3-bcd3-4242-9266-0b870288e609",
    "country": "Local"
  },
  {
    "time": 1779078366.4549491,
    "visitor_id": "1cae6bb3-bcd3-4242-9266-0b870288e609",
    "country": "Local"
  },
  {
    "time": 1779078474.859093,
    "visitor_id": "1cae6bb3-bcd3-4242-9266-0b870288e609",
    "country": "Local"
  },
  {
    "time": 1779078476.514174,
    "visitor_id": "1cae6bb3-bcd3-4242-9266-0b870288e609",
    "country": "Local"
  },
  {
    "time": 1779079382.308566,
    "visitor_id": "1cae6bb3-bcd3-4242-9266-0b870288e609",
    "country": "Local"
  },
  {
    "time": 1779079399.010133,
    "visitor_id": "1cae6bb3-bcd3-4242-9266-0b870288e609",
    "country": "Local"
  },
  {
    "time": 1779080030.8624508,
    "visitor_id": "1cae6bb3-bcd3-4242-9266-0b870288e609",
    "country": "Local"
  },
  {
    "time": 1779080568.9432929,
    "visitor_id": "1cae6bb3-bcd3-4242-9266-0b870288e609",
    "country": "Local"
  },
  {
    "time": 1779080861.0629508,
    "visitor_id": "1cae6bb3-bcd3-4242-9266-0b870288e609",
    "country": "Local"
  },
  {
    "time": 1779081601.4175029,
    "visitor_id": "1cae6bb3-bcd3-4242-9266-0b870288e609",
    "country": "Local"
  },
  {
    "time": 1779081937.099905,
    "visitor_id": "1cae6bb3-bcd3-4242-9266-0b870288e609",
    "country": "Local"
  },
  {
    "time": 1779082240.0469508,
    "visitor_id": "1cae6bb3-bcd3-4242-9266-0b870288e609",
    "country": "Local"
  },
  {
    "time": 1779082387.845855,
    "visitor_id": "1cae6bb3-bcd3-4242-9266-0b870288e609",
    "country": "Local"
  },
  {
    "time": 1779082429.194386,
    "visitor_id": "1cae6bb3-bcd3-4242-9266-0b870288e609",
    "country": "Local"
  },
  {
    "time": 1779105690.990029,
    "visitor_id": "1cae6bb3-bcd3-4242-9266-0b870288e609",
    "country": "Local"
  },
  {
    "time": 1779105701.321012,
    "visitor_id": "1cae6bb3-bcd3-4242-9266-0b870288e609",
    "country": "Local"
  },
  {
    "time": 1779107043.816973,
    "visitor_id": "1cae6bb3-bcd3-4242-9266-0b870288e609",
    "country": "Local"
  },
  {
    "time": 1779107679.630445,
    "visitor_id": "1cae6bb3-bcd3-4242-9266-0b870288e609",
    "country": "Local"
  },
  {
    "time": 1779107797.433721,
    "visitor_id": "1cae6bb3-bcd3-4242-9266-0b870288e609",
    "country": "Local"
  },
  {
    "time": 1779107875.730538,
    "visitor_id": "1cae6bb3-bcd3-4242-9266-0b870288e609",
    "country": "Local"
  },
  {
    "time": 1779108098.698549,
    "visitor_id": "1cae6bb3-bcd3-4242-9266-0b870288e609",
    "country": "Local"
  },
  {
    "time": 1779108109.183084,
    "visitor_id": "1cae6bb3-bcd3-4242-9266-0b870288e609",
    "country": "Local"
  },
  {
    "time": 1779108135.075983,
    "visitor_id": "1cae6bb3-bcd3-4242-9266-0b870288e609",
    "country": "Local"
  },
  {
    "time": 1779108612.2279942,
    "visitor_id": "1cae6bb3-bcd3-4242-9266-0b870288e609",
    "country": "Local"
  },
  {
    "time": 1779108670.67857,
    "visitor_id": "1cae6bb3-bcd3-4242-9266-0b870288e609",
    "country": "Local"
  },
  {
    "time": 1779108682.472568,
    "visitor_id": "1cae6bb3-bcd3-4242-9266-0b870288e609",
    "country": "Local"
  },
  {
    "time": 1779110587.7421691,
    "visitor_id": "1cae6bb3-bcd3-4242-9266-0b870288e609",
    "country": "Local"
  },
  {
    "time": 1779110660.614379,
    "visitor_id": "1cae6bb3-bcd3-4242-9266-0b870288e609",
    "country": "Local"
  },
  {
    "time": 1779110735.5350459,
    "visitor_id": "1cae6bb3-bcd3-4242-9266-0b870288e609",
    "country": "Local"
  },
  {
    "time": 1779110806.528395,
    "visitor_id": "1cae6bb3-bcd3-4242-9266-0b870288e609",
    "country": "Local"
  },
  {
    "time": 1779111044.104,
    "visitor_id": "1cae6bb3-bcd3-4242-9266-0b870288e609",
    "country": "Local"
  },
  {
    "time": 1779111183.930326,
    "visitor_id": "1cae6bb3-bcd3-4242-9266-0b870288e609",
    "country": "Local"
  },
  {
    "time": 1779111251.1079638,
    "visitor_id": "1cae6bb3-bcd3-4242-9266-0b870288e609",
    "country": "Local"
  },
  {
    "time": 1779111424.3519528,
    "visitor_id": "1cae6bb3-bcd3-4242-9266-0b870288e609",
    "country": "Local"
  },
  {
    "time": 1779111564.007089,
    "visitor_id": "1cae6bb3-bcd3-4242-9266-0b870288e609",
    "country": "Local"
  },
  {
    "time": 1779111603.822379,
    "visitor_id": "1cae6bb3-bcd3-4242-9266-0b870288e609",
    "country": "Local"
  },
  {
    "time": 1779111756.21411,
    "visitor_id": "1cae6bb3-bcd3-4242-9266-0b870288e609",
    "country": "Local"
  },
  {
    "time": 1779111894.666246,
    "visitor_id": "1cae6bb3-bcd3-4242-9266-0b870288e609",
    "country": "Local"
  },
  {
    "time": 1779111987.6822028,
    "visitor_id": "1cae6bb3-bcd3-4242-9266-0b870288e609",
    "country": "Local"
  },
  {
    "time": 1779111995.666614,
    "visitor_id": "1cae6bb3-bcd3-4242-9266-0b870288e609",
    "country": "Local"
  },
  {
    "time": 1779112337.412852,
    "visitor_id": "1cae6bb3-bcd3-4242-9266-0b870288e609",
    "country": "Local"
  },
  {
    "time": 1779112348.43241,
    "visitor_id": "1cae6bb3-bcd3-4242-9266-0b870288e609",
    "country": "Local"
  },
  {
    "time": 1779112403.511403,
    "visitor_id": "1cae6bb3-bcd3-4242-9266-0b870288e609",
    "country": "Local"
  },
  {
    "time": 1779112634.677875,
    "visitor_id": "1cae6bb3-bcd3-4242-9266-0b870288e609",
    "country": "Local"
  },
  {
    "time": 1779113374.923,
    "visitor_id": "1cae6bb3-bcd3-4242-9266-0b870288e609",
    "country": "Local"
  },
  {
    "time": 1779113408.7321768,
    "visitor_id": "1cae6bb3-bcd3-4242-9266-0b870288e609",
    "country": "Local"
  },
  {
    "time": 1779113416.093197,
    "visitor_id": "1cae6bb3-bcd3-4242-9266-0b870288e609",
    "country": "Local"
  },
  {
    "time": 1779113705.507432,
    "visitor_id": "1cae6bb3-bcd3-4242-9266-0b870288e609",
    "country": "Local"
  },
  {
    "time": 1779113713.056007,
    "visitor_id": "1cae6bb3-bcd3-4242-9266-0b870288e609",
    "country": "Local"
  },
  {
    "time": 1779113993.678113,
    "visitor_id": "1cae6bb3-bcd3-4242-9266-0b870288e609",
    "country": "Local"
  },
  {
    "time": 1779117355.079347,
    "visitor_id": "1cae6bb3-bcd3-4242-9266-0b870288e609",
    "country": "Local"
  },
  {
    "time": 1779117372.216726,
    "visitor_id": "1cae6bb3-bcd3-4242-9266-0b870288e609",
    "country": "Local"
  },
  {
    "time": 1779117376.9946141,
    "visitor_id": "1cae6bb3-bcd3-4242-9266-0b870288e609",
    "country": "Local"
  },
  {
    "time": 1779117576.625365,
    "visitor_id": "1cae6bb3-bcd3-4242-9266-0b870288e609",
    "country": "Local"
  },
  {
    "time": 1779117732.4977212,
    "visitor_id": "1cae6bb3-bcd3-4242-9266-0b870288e609",
    "country": "Local"
  },
  {
    "time": 1779118145.719429,
    "visitor_id": "1cae6bb3-bcd3-4242-9266-0b870288e609",
    "country": "Local"
  },
  {
    "time": 1779118156.28999,
    "visitor_id": "1cae6bb3-bcd3-4242-9266-0b870288e609",
    "country": "Local"
  },
  {
    "time": 1779118217.684587,
    "visitor_id": "1cae6bb3-bcd3-4242-9266-0b870288e609",
    "country": "Local"
  },
  {
    "time": 1779118429.797993,
    "visitor_id": "1cae6bb3-bcd3-4242-9266-0b870288e609",
    "country": "Local"
  },
  {
    "time": 1779118938.4921548,
    "visitor_id": "1cae6bb3-bcd3-4242-9266-0b870288e609",
    "country": "Local"
  },
  {
    "time": 1779119075.702122,
    "visitor_id": "1cae6bb3-bcd3-4242-9266-0b870288e609",
    "country": "Local"
  },
  {
    "time": 1779119585.606912,
    "visitor_id": "1cae6bb3-bcd3-4242-9266-0b870288e609",
    "country": "Local"
  },
  {
    "time": 1779120104.009113,
    "visitor_id": "1cae6bb3-bcd3-4242-9266-0b870288e609",
    "country": "Local"
  },
  {
    "time": 1779120172.973343,
    "visitor_id": "1cae6bb3-bcd3-4242-9266-0b870288e609",
    "country": "Local"
  },
  {
    "time": 1779120339.5258172,
    "visitor_id": "1cae6bb3-bcd3-4242-9266-0b870288e609",
    "country": "Local"
  },
  {
    "time": 1779120415.953703,
    "visitor_id": "1cae6bb3-bcd3-4242-9266-0b870288e609",
    "country": "Local"
  },
  {
    "time": 1779120417.578143,
    "visitor_id": "1cae6bb3-bcd3-4242-9266-0b870288e609",
    "country": "Local"
  },
  {
    "time": 1779120419.215379,
    "visitor_id": "1cae6bb3-bcd3-4242-9266-0b870288e609",
    "country": "Local"
  },
  {
    "time": 1779120422.46927,
    "visitor_id": "1cae6bb3-bcd3-4242-9266-0b870288e609",
    "country": "Local"
  },
  {
    "time": 1779120475.336687,
    "visitor_id": "1cae6bb3-bcd3-4242-9266-0b870288e609",
    "country": "Local"
  },
  {
    "time": 1779120525.816767,
    "visitor_id": "1cae6bb3-bcd3-4242-9266-0b870288e609",
    "country": "Local"
  },
  {
    "time": 1779120544.066269,
    "visitor_id": "1cae6bb3-bcd3-4242-9266-0b870288e609",
    "country": "Local"
  },
  {
    "time": 1779120763.334668,
    "visitor_id": "1cae6bb3-bcd3-4242-9266-0b870288e609",
    "country": "Local"
  },
  {
    "time": 1779121046.291307,
    "visitor_id": "1cae6bb3-bcd3-4242-9266-0b870288e609",
    "country": "Local"
  },
  {
    "time": 1779121084.699738,
    "visitor_id": "1cae6bb3-bcd3-4242-9266-0b870288e609",
    "country": "Local"
  },
  {
    "time": 1779121086.3076239,
    "visitor_id": "1cae6bb3-bcd3-4242-9266-0b870288e609",
    "country": "Local"
  },
  {
    "time": 1779121131.044412,
    "visitor_id": "1cae6bb3-bcd3-4242-9266-0b870288e609",
    "country": "Local"
  },
  {
    "time": 1779121582.054347,
    "visitor_id": "1cae6bb3-bcd3-4242-9266-0b870288e609",
    "country": "Local"
  },
  {
    "time": 1779121585.7956748,
    "visitor_id": "1cae6bb3-bcd3-4242-9266-0b870288e609",
    "country": "Local"
  },
  {
    "time": 1779121790.992099,
    "visitor_id": "1cae6bb3-bcd3-4242-9266-0b870288e609",
    "country": "Local"
  },
  {
    "time": 1779121820.251724,
    "visitor_id": "1cae6bb3-bcd3-4242-9266-0b870288e609",
    "country": "Local"
  },
  {
    "time": 1779121821.5961092,
    "visitor_id": "1cae6bb3-bcd3-4242-9266-0b870288e609",
    "country": "Local"
  },
  {
    "time": 1779121822.4638212,
    "visitor_id": "1cae6bb3-bcd3-4242-9266-0b870288e609",
    "country": "Local"
  },
  {
    "time": 1779121823.178477,
    "visitor_id": "1cae6bb3-bcd3-4242-9266-0b870288e609",
    "country": "Local"
  },
  {
    "time": 1779121984.80537,
    "visitor_id": "1cae6bb3-bcd3-4242-9266-0b870288e609",
    "country": "Local"
  },
  {
    "time": 1779121998.603648,
    "visitor_id": "1cae6bb3-bcd3-4242-9266-0b870288e609",
    "country": "Local"
  },
  {
    "time": 1779121999.629453,
    "visitor_id": "1cae6bb3-bcd3-4242-9266-0b870288e609",
    "country": "Local"
  },
  {
    "time": 1779122000.259609,
    "visitor_id": "1cae6bb3-bcd3-4242-9266-0b870288e609",
    "country": "Local"
  },
  {
    "time": 1779122550.3030348,
    "visitor_id": "1cae6bb3-bcd3-4242-9266-0b870288e609",
    "country": "Local"
  },
  {
    "time": 1779124804.609099,
    "visitor_id": "1cae6bb3-bcd3-4242-9266-0b870288e609",
    "country": "Local"
  },
  {
    "time": 1779124820.751171,
    "visitor_id": "1cae6bb3-bcd3-4242-9266-0b870288e609",
    "country": "Local"
  },
  {
    "time": 1779124827.916308,
    "visitor_id": "1cae6bb3-bcd3-4242-9266-0b870288e609",
    "country": "Local"
  },
  {
    "time": 1779146611.483212,
    "visitor_id": "1cae6bb3-bcd3-4242-9266-0b870288e609",
    "country": "Local"
  }
]